<?xml version="1.0" encoding="UTF-8"?>

<Defs>
    <KCSG.StructureLayoutDef>
        <defName>seanbaeg_is_this</defName>
        <isStorage>true</isStorage>
        <spawnConduits>false</spawnConduits>
        <modExtensions>
            <li Class="MSSFP.ModExtensions.StructureDefModExtension">
                <author>seanbaeg</author>
                <spawnedPawns>
                    <li>
                        <kindDef>Colonist</kindDef>
                        <nameInt Class="NameTriple">
                            <first>Varkie</first>
                            <nick />
                            <last>Liefe</last>
                        </nameInt>
                        <gender>Female</gender>
                        <age>50</age>
                        <inventory />
                        <equipment IsNull="True" />
                        <beardDef>NoBeard</beardDef>
                        <faceTattoo>NoTattoo_Face</faceTattoo>
                        <bodyTattoo>NoTattoo_Body</bodyTattoo>
                        <genes>
                            <li>Skin_Melanin1</li>
                            <li>Hair_MidBlack</li>
                        </genes>
                        <spawnCell>(115, 0, 127)</spawnCell>
                    </li>
                    <li>
                        <kindDef>Colonist</kindDef>
                        <nameInt Class="NameTriple">
                            <first>Willow</first>
                            <nick>Boots</nick>
                            <last>McCarty</last>
                        </nameInt>
                        <gender>Female</gender>
                        <age>37</age>
                        <inventory />
                        <equipment IsNull="True" />
                        <beardDef>NoBeard</beardDef>
                        <faceTattoo>NoTattoo_Face</faceTattoo>
                        <bodyTattoo>NoTattoo_Body</bodyTattoo>
                        <genes>
                            <li>Skin_Melanin1</li>
                            <li>Hair_DarkBlack</li>
                        </genes>
                        <spawnCell>(91, 0, 138)</spawnCell>
                    </li>
                    <li>
                        <kindDef>Colonist</kindDef>
                        <nameInt Class="NameTriple">
                            <first>Victoria</first>
                            <nick>Vicky</nick>
                            <last>Louene</last>
                        </nameInt>
                        <gender>Female</gender>
                        <age>45</age>
                        <inventory />
                        <equipment IsNull="True" />
                        <beardDef>NoBeard</beardDef>
                        <faceTattoo>NoTattoo_Face</faceTattoo>
                        <bodyTattoo>NoTattoo_Body</bodyTattoo>
                        <genes>
                            <li>Skin_Melanin4</li>
                            <li>Hair_DarkReddish</li>
                        </genes>
                        <spawnCell>(93, 0, 137)</spawnCell>
                    </li>
                </spawnedPawns>
            </li>
        </modExtensions>
        <layouts>
            <li>
                <li>.,.,.,.,.,.,.,.,.,.,.,.,.,.,.,.,.,.,.,.,.,.,.,.,.,.,.,.,.,.,.,Boomalope,.,.,.,.,.,.,.,.,.,.,.,.,.,.,.,.,.,.,.,.,.,.,.,.,.,.,.,.,.,.,.,.,.,.,.,.,.,.,.,.,.,.,.,.,.,.</li>
                <li>.,.,.,.,.,.,.,.,.,.,.,.,.,.,.,.,.,.,.,.,.,.,.,.,.,.,.,.,Boomalope,.,.,.,.,.,.,.,.,.,.,.,.,.,.,.,.,.,.,.,.,.,.,.,.,.,.,.,.,.,.,.,.,.,.,.,.,.,.,.,.,.,.,.,.,.,.,.,.,.</li>
                <li>.,.,.,.,.,.,.,.,.,.,.,.,.,.,.,.,.,.,.,.,.,.,.,.,.,.,.,.,.,.,.,.,Boomalope,.,.,.,.,.,.,.,.,.,.,.,.,.,.,.,.,.,.,.,.,.,.,.,.,.,.,.,.,.,.,.,.,.,.,.,.,.,.,.,.,.,.,.,.,.</li>
                <li>.,.,.,.,.,.,.,.,.,.,.,.,.,.,.,.,.,.,.,.,.,.,.,.,.,.,.,.,.,.,.,.,.,.,.,.,.,.,.,.,.,.,.,.,.,.,.,.,.,.,.,.,.,.,.,.,.,.,.,.,.,.,.,.,.,.,.,.,.,.,.,.,.,.,.,.,.,.</li>
                <li>.,.,.,.,.,.,.,.,.,.,.,.,.,.,.,.,.,.,.,.,.,.,.,.,.,.,.,.,.,.,.,.,.,.,.,.,.,.,.,.,.,.,.,.,.,.,.,.,.,.,.,.,.,.,.,.,.,.,.,.,.,.,.,.,.,.,.,.,.,.,.,.,.,.,.,.,.,.</li>
                <li>.,.,.,.,.,.,Wall_BlocksGranite,Wall_BlocksGranite,Wall_BlocksGranite,Wall_BlocksGranite,Wall_BlocksGranite,Door_Steel,Wall_BlocksGranite,Wall_BlocksGranite,Wall_BlocksGranite,Wall_BlocksGranite,Wall_BlocksGranite,.,.,.,Wall_BlocksGranite,Wall_BlocksGranite,Wall_BlocksGranite,Wall_BlocksGranite,Wall_BlocksGranite,Door_Steel,Wall_BlocksGranite,Wall_BlocksGranite,Wall_BlocksGranite,Wall_BlocksGranite,Wall_BlocksGranite,.,.,.,.,.,Boomalope,.,.,.,Iguana,.,.,Wall_BlocksGranite,Wall_BlocksGranite,Wall_BlocksGranite,Wall_BlocksGranite,Wall_BlocksGranite,Door_Steel,Wall_BlocksGranite,Wall_BlocksGranite,Wall_BlocksGranite,Wall_BlocksGranite,Wall_BlocksGranite,.,.,.,Wall_BlocksGranite,Wall_BlocksGranite,Wall_BlocksGranite,Wall_BlocksGranite,Wall_BlocksGranite,Wall_BlocksGranite,Wall_BlocksGranite,Wall_BlocksGranite,Wall_BlocksGranite,Wall_BlocksGranite,Wall_BlocksGranite,Wall_BlocksGranite,Wall_BlocksGranite,Wall_BlocksGranite,Wall_BlocksGranite,Wall_BlocksGranite,Wall_BlocksGranite,Wall_BlocksGranite,Wall_BlocksGranite,BlocksGranite,.</li>
                <li>.,.,.,.,.,.,Wall_BlocksGranite,.,.,.,.,.,.,.,.,.,Wall_BlocksGranite,.,.,.,Wall_BlocksGranite,.,.,.,.,.,.,.,.,.,Wall_BlocksGranite,.,.,.,.,.,.,.,.,.,.,.,.,Wall_BlocksGranite,.,.,.,.,.,.,.,.,.,Wall_BlocksGranite,.,.,.,Wall_BlocksGranite,.,.,.,.,.,.,.,HiddenConduit,.,.,.,.,.,.,.,.,.,Wall_BlocksGranite,.,.</li>
                <li>.,.,.,.,.,.,Wall_BlocksGranite,.,.,.,.,.,.,.,.,.,Wall_BlocksGranite,.,.,.,Wall_BlocksGranite,.,.,.,.,.,.,.,.,.,Wall_BlocksGranite,.,.,.,.,.,.,.,.,.,.,.,.,Wall_BlocksGranite,Bed_WoodLog_East,.,.,.,.,.,.,.,.,Wall_BlocksGranite,.,.,.,Wall_BlocksGranite,.,.,.,.,.,.,.,HiddenConduit,.,.,.,.,.,.,.,.,.,Wall_BlocksGranite,.,.</li>
                <li>.,.,.,.,.,.,Wall_BlocksGranite,.,.,.,.,.,.,.,.,.,Wall_BlocksGranite,.,.,.,Wall_BlocksGranite,.,.,.,.,.,.,.,.,.,Wall_BlocksGranite,.,.,.,.,.,.,.,.,.,.,.,.,Wall_BlocksGranite,.,.,.,.,.,.,.,.,.,Wall_BlocksGranite,.,.,.,Wall_BlocksGranite,.,.,.,.,.,.,.,HiddenConduit,.,.,.,.,.,.,.,.,.,Wall_BlocksGranite,.,.</li>
                <li>.,.,.,.,.,.,Wall_BlocksGranite,.,.,.,.,.,.,.,.,.,Wall_BlocksGranite,.,.,.,Wall_BlocksGranite,.,.,.,.,.,.,.,.,.,Wall_BlocksGranite,.,.,.,.,.,.,.,.,.,.,.,.,Wall_BlocksGranite,Bed_WoodLog_East,.,.,.,.,.,.,.,.,Wall_BlocksGranite,.,.,.,Wall_BlocksGranite,.,.,.,.,.,.,.,Donkey,VitalsMonitor_West,.,.,.,.,.,.,.,.,Wall_BlocksGranite,.,.</li>
                <li>.,.,.,.,.,.,Wall_BlocksGranite,.,.,.,.,.,DoubleBed_WoodLog_South,.,.,.,Wall_BlocksGranite,.,.,.,Wall_BlocksGranite,.,.,.,.,.,DoubleBed_WoodLog_South,.,.,.,Wall_BlocksGranite,.,.,.,.,.,.,.,.,.,.,.,.,Wall_BlocksGranite,.,.,.,.,.,.,.,.,.,Wall_BlocksGranite,.,.,.,Door_Steel,.,.,.,.,.,.,.,HiddenConduit,HospitalBed_Steel_West,StandingLamp,.,.,.,.,.,.,.,Wall_BlocksGranite,.,.</li>
                <li>.,.,.,.,.,.,Wall_BlocksGranite,.,.,.,.,.,.,.,.,.,Wall_BlocksGranite,.,.,.,Wall_BlocksGranite,.,.,.,.,.,.,.,.,.,Wall_BlocksGranite,.,.,.,.,.,.,.,.,.,.,.,.,Wall_BlocksGranite,Bed_WoodLog_East,.,.,.,.,.,.,.,.,Wall_BlocksGranite,.,.,.,Wall_BlocksGranite,.,.,.,.,.,.,.,HiddenConduit,.,.,.,.,.,.,.,.,.,Wall_BlocksGranite,.,.</li>
                <li>.,.,.,.,.,.,Wall_BlocksGranite,.,.,.,.,.,.,.,.,.,Wall_BlocksGranite,.,.,.,Wall_BlocksGranite,.,.,.,.,.,.,.,.,.,Wall_BlocksGranite,.,.,.,.,.,.,.,.,.,.,.,.,Wall_BlocksGranite,.,.,.,.,.,.,.,.,.,Wall_BlocksGranite,.,.,.,Wall_BlocksGranite,.,.,.,.,.,.,.,HiddenConduit,.,.,.,BlocksLimestone,.,.,.,.,.,Wall_BlocksGranite,.,.</li>
                <li>.,.,.,.,.,.,Wall_BlocksGranite,.,.,.,.,.,.,.,.,.,Wall_BlocksGranite,.,.,.,Wall_BlocksGranite,.,.,.,.,.,.,.,.,.,Wall_BlocksGranite,.,.,.,.,.,.,.,.,.,.,.,.,Wall_BlocksGranite,.,.,.,.,.,.,.,.,.,Wall_BlocksGranite,.,.,.,Wall_BlocksGranite,.,.,Crib_WoodLog_South,.,Crib_WoodLog_South,.,.,HiddenConduit,.,.,.,.,.,.,.,.,BlocksLimestone,Wall_BlocksGranite,.,.</li>
                <li>.,.,.,.,.,.,Wall_BlocksGranite,Wall_BlocksGranite,Wall_BlocksGranite,Wall_BlocksGranite,Wall_BlocksGranite,Wall_BlocksGranite,Wall_BlocksGranite,Wall_BlocksGranite,Wall_BlocksGranite,Wall_BlocksGranite,Wall_BlocksGranite,.,.,.,Wall_BlocksGranite,Wall_BlocksGranite,Wall_BlocksGranite,Wall_BlocksGranite,Wall_BlocksGranite,Wall_BlocksGranite,Wall_BlocksGranite,Wall_BlocksGranite,Wall_BlocksGranite,Wall_BlocksGranite,Wall_BlocksGranite,.,.,.,.,.,.,.,.,.,.,.,.,Wall_BlocksGranite,Wall_BlocksGranite,Wall_BlocksGranite,Wall_BlocksGranite,Wall_BlocksGranite,Wall_BlocksGranite,Wall_BlocksGranite,Wall_BlocksGranite,Wall_BlocksGranite,Wall_BlocksGranite,Wall_BlocksGranite,HiddenConduit,HiddenConduit,HiddenConduit,Wall_BlocksGranite,.,.,.,.,.,.,.,HiddenConduit,.,.,HospitalBed_Steel_South,VitalsMonitor_South,StandingLamp,.,HospitalBed_Steel_South,VitalsMonitor_South,.,Wall_BlocksGranite,.,.</li>
                <li>.,.,.,.,.,.,Wall_BlocksGranite,.,.,.,.,.,.,.,.,.,Wall_BlocksGranite,.,.,.,Wall_BlocksGranite,.,.,.,.,.,.,.,.,.,Wall_BlocksGranite,.,.,.,.,.,.,.,.,.,.,.,.,Wall_BlocksGranite,WoodLog,.,.,.,.,.,.,.,.,Wall_BlocksGranite,.,.,.,Wall_BlocksGranite,Wall_BlocksGranite,Wall_BlocksGranite,Wall_BlocksGranite,Wall_BlocksGranite,Wall_BlocksGranite,Wall_BlocksGranite,Wall_BlocksGranite,Wall_BlocksGranite,Wall_BlocksGranite,Wall_BlocksGranite,Wall_BlocksGranite,Wall_BlocksGranite,Wall_BlocksGranite,Wall_BlocksGranite,Wall_BlocksGranite,Wall_BlocksGranite,Wall_BlocksGranite,Wall_BlocksGranite,.,.</li>
                <li>.,.,.,.,.,.,Wall_BlocksGranite,.,.,.,.,.,.,.,.,.,Wall_BlocksGranite,.,.,.,Wall_BlocksGranite,.,.,.,.,.,.,.,.,.,Wall_BlocksGranite,.,.,.,.,.,.,.,.,.,.,.,.,Wall_BlocksGranite,.,.,.,.,.,.,.,.,.,Wall_BlocksGranite,.,.,.,BlocksGranite,BlocksGranite,BlocksGranite,BlocksGranite,BlocksGranite,BlocksGranite,BlocksGranite,BlocksGranite,BlocksGranite,BlocksGranite,BlocksGranite,BlocksGranite,BlocksGranite,BlocksGranite,BlocksGranite,BlocksGranite,BlocksGranite,BlocksGranite,BlocksGranite,.,.</li>
                <li>.,.,.,.,.,.,Wall_BlocksGranite,.,.,.,.,.,.,.,.,.,Wall_BlocksGranite,.,.,.,Wall_BlocksGranite,.,.,.,.,.,.,.,.,.,Wall_BlocksGranite,.,.,.,.,.,.,.,.,.,.,.,.,Wall_BlocksGranite,Bed_WoodLog_East,.,.,.,.,.,.,.,.,Wall_BlocksGranite,.,.,.,.,.,.,.,.,.,.,.,.,.,.,.,.,.,.,.,.,.,.,.,.</li>
                <li>.,.,.,.,.,.,Wall_BlocksGranite,.,.,.,DoubleBed_WoodLog_North,.,.,.,.,.,Wall_BlocksGranite,.,.,.,Wall_BlocksGranite,.,.,.,.,DoubleBed_WoodLog_North,.,.,.,.,Wall_BlocksGranite,.,.,.,.,.,.,.,.,.,.,.,.,Wall_BlocksGranite,.,.,.,.,.,.,.,.,.,Wall_BlocksGranite,.,.,.,.,.,.,.,.,.,.,.,Colonist,.,.,.,BlocksSlate,.,.,.,.,.,.,.,.</li>
                <li>.,.,.,.,.,.,Wall_BlocksGranite,.,.,.,.,.,.,.,.,.,Wall_BlocksGranite,.,.,.,Wall_BlocksGranite,.,.,.,.,.,.,.,.,.,Wall_BlocksGranite,.,SteamGeyser,.,.,.,.,.,.,.,.,.,.,Wall_BlocksGranite,Bed_WoodLog_East,.,.,.,.,.,.,.,.,Wall_BlocksGranite,.,.,.,.,.,.,.,.,.,.,.,.,.,.,.,.,.,.,.,.,.,.,.,.</li>
                <li>.,.,.,.,.,.,Wall_BlocksGranite,.,.,.,.,.,.,.,.,.,Wall_BlocksGranite,.,.,.,Wall_BlocksGranite,.,.,.,.,.,.,.,.,.,Wall_BlocksGranite,.,.,.,.,.,.,.,.,.,.,.,.,Wall_BlocksGranite,.,.,.,.,.,.,.,.,.,Wall_BlocksGranite,.,.,.,.,.,.,.,.,.,.,.,.,.,.,.,.,.,.,.,.,.,.,.,.</li>
                <li>.,.,.,.,.,.,Wall_BlocksGranite,.,.,.,.,.,.,.,.,.,Wall_BlocksGranite,.,.,.,Wall_BlocksGranite,.,.,.,.,.,.,.,.,.,Wall_BlocksGranite,.,.,.,.,.,.,.,.,.,.,.,.,Wall_BlocksGranite,Bed_WoodLog_East,.,.,.,.,.,.,.,.,Wall_BlocksGranite,.,.,.,.,.,.,.,.,.,.,.,.,.,.,.,.,.,.,.,.,.,.,.,.</li>
                <li>.,.,.,.,.,.,Wall_BlocksGranite,.,.,.,.,.,.,.,.,.,Wall_BlocksGranite,.,.,.,Wall_BlocksGranite,.,.,.,.,.,.,.,.,.,Wall_BlocksGranite,.,.,.,.,.,.,.,.,.,.,.,.,Wall_BlocksGranite,.,.,.,.,.,.,.,.,.,Wall_BlocksGranite,.,.,.,.,.,.,.,.,.,.,.,.,.,.,.,.,.,.,.,.,.,BlocksLimestone,.,.</li>
                <li>.,.,.,.,.,.,Wall_BlocksGranite,Wall_BlocksGranite,Wall_BlocksGranite,Wall_BlocksGranite,Wall_BlocksGranite,Door_Steel,Wall_BlocksGranite,Wall_BlocksGranite,Wall_BlocksGranite,Wall_BlocksGranite,Wall_BlocksGranite,.,.,.,Wall_BlocksGranite,Wall_BlocksGranite,Wall_BlocksGranite,Wall_BlocksGranite,Wall_BlocksGranite,Door_Steel,Wall_BlocksGranite,Wall_BlocksGranite,Wall_BlocksGranite,Wall_BlocksGranite,Wall_BlocksGranite,.,.,.,.,.,.,.,.,.,.,.,.,Wall_BlocksGranite,Wall_BlocksGranite,Wall_BlocksGranite,Wall_BlocksGranite,Wall_BlocksGranite,Door_Steel,Wall_BlocksGranite,Wall_BlocksGranite,Wall_BlocksGranite,Wall_BlocksGranite,Wall_BlocksGranite,.,.,.,.,.,.,.,.,.,.,.,.,.,.,.,.,.,.,.,.,.,.,.,.</li>
                <li>.,.,.,.,.,.,.,.,.,.,.,.,.,.,.,.,.,.,.,.,HiddenConduit,.,.,.,.,.,.,.,.,.,.,.,.,.,.,.,.,.,.,.,.,.,.,HiddenConduit,.,.,.,.,.,.,.,.,.,.,.,.,Squirrel,.,.,.,.,.,.,.,.,.,.,.,.,.,.,.,.,.,.,.,.,.</li>
                <li>.,.,.,.,.,.,.,.,.,.,.,.,.,.,.,.,.,.,.,.,HiddenConduit,.,.,.,.,.,.,.,.,.,.,.,.,.,.,.,.,.,.,.,.,.,.,HiddenConduit,.,.,.,.,.,.,.,.,.,.,.,.,.,.,.,.,.,.,.,.,.,.,.,.,.,.,.,.,.,.,.,.,.,.</li>
                <li>.,.,.,.,.,.,.,.,.,.,.,.,.,.,.,.,.,.,.,.,HiddenConduit,.,.,.,.,.,.,.,.,.,.,.,.,.,.,.,.,.,.,.,.,.,.,HiddenConduit,.,.,.,.,.,.,.,.,.,.,.,.,.,.,.,.,.,.,.,.,.,.,.,.,.,.,.,.,.,.,.,.,.,.</li>
                <li>.,.,.,.,.,.,.,.,.,.,.,.,.,.,.,.,.,.,.,.,HiddenConduit,.,.,.,.,.,.,.,.,.,.,.,.,.,.,.,.,.,.,.,.,.,.,HiddenConduit,.,.,.,.,.,.,.,.,.,.,.,.,.,.,.,.,.,.,.,.,.,.,.,.,.,.,.,.,.,.,.,.,.,.</li>
                <li>.,.,.,.,.,.,.,.,.,.,.,.,.,.,.,.,.,.,.,.,HiddenConduit,.,.,.,.,.,.,.,.,.,.,.,.,.,.,.,.,.,.,.,.,.,.,HiddenConduit,.,.,.,.,.,.,.,.,.,.,.,.,.,.,.,.,.,.,.,.,.,.,.,.,.,.,.,.,.,.,.,.,.,.</li>
                <li>.,.,.,.,.,.,.,.,.,.,.,.,.,.,.,.,.,.,.,.,HiddenConduit,.,.,.,.,.,.,.,.,.,.,.,.,.,.,.,.,.,.,.,.,.,.,HiddenConduit,.,.,.,.,.,.,.,.,.,.,.,.,.,.,.,.,.,.,.,.,.,.,.,.,.,.,.,.,.,.,.,.,.,.</li>
                <li>.,.,.,.,.,.,.,.,.,.,.,.,.,.,.,.,.,.,.,.,HiddenConduit,.,.,.,.,.,.,.,.,.,.,.,.,.,.,.,.,.,.,.,.,.,.,HiddenConduit,.,.,.,.,.,.,.,.,.,.,.,.,.,.,.,.,.,.,.,.,.,.,.,.,.,.,.,.,.,.,.,.,.,.</li>
                <li>.,.,.,.,.,.,.,.,.,.,.,.,.,Wall_BlocksGranite,Wall_BlocksGranite,Wall_BlocksGranite,Wall_BlocksGranite,Wall_BlocksGranite,Door_Steel,Wall_BlocksGranite,Wall_BlocksGranite,Wall_BlocksGranite,Wall_BlocksGranite,Wall_BlocksGranite,HiddenConduit,HiddenConduit,.,.,.,.,HiddenConduit,HiddenConduit,HiddenConduit,HiddenConduit,HiddenConduit,HiddenConduit,HiddenConduit,HiddenConduit,HiddenConduit,HiddenConduit,HiddenConduit,HiddenConduit,HiddenConduit,Wall_BlocksGranite,Wall_BlocksGranite,Wall_BlocksGranite,Wall_BlocksGranite,Wall_BlocksGranite,Door_Steel,Wall_BlocksGranite,Wall_BlocksGranite,Wall_BlocksGranite,Wall_BlocksGranite,Wall_BlocksGranite,HiddenConduit,HiddenConduit,HiddenConduit,Wall_BlocksGranite,Wall_BlocksGranite,Wall_BlocksGranite,Wall_BlocksGranite,Wall_BlocksGranite,Door_Steel,Wall_BlocksGranite,Wall_BlocksGranite,Wall_BlocksGranite,Wall_BlocksGranite,Wall_BlocksGranite,.,.,.,.,.,.,.,.,.,.</li>
                <li>.,.,.,.,.,.,.,.,.,.,.,.,.,Wall_BlocksGranite,BlocksGranite,Steel,.,.,.,Battery_North,Battery_North,Battery_North,Battery_North,Wall_BlocksGranite,.,.,.,SolarGenerator,.,.,.,.,.,.,.,.,.,.,.,.,.,.,.,Wall_BlocksGranite,.,.,.,.,.,.,.,.,.,Wall_BlocksGranite,.,.,.,Wall_BlocksGranite,.,.,.,.,.,.,.,.,.,Wall_BlocksGranite,.,.,.,.,.,.,.,.,.,.</li>
                <li>.,.,.,.,.,.,.,.,.,.,.,.,.,Wall_BlocksGranite,BlocksGranite,.,.,.,.,.,.,.,.,Wall_BlocksGranite,.,.,.,.,.,.,.,.,.,.,.,.,.,.,.,.,.,.,.,Wall_BlocksGranite,.,.,.,.,.,.,.,.,.,Wall_BlocksGranite,.,.,.,Wall_BlocksGranite,.,.,.,.,.,.,.,.,.,Wall_BlocksGranite,.,.,.,.,.,.,.,.,.,.</li>
                <li>.,.,.,.,.,.,.,.,.,.,.,.,.,Wall_BlocksGranite,BlocksGranite,.,.,.,.,.,.,.,.,Wall_BlocksGranite,.,.,.,.,.,.,.,.,.,.,.,.,.,.,.,.,.,.,.,Wall_BlocksGranite,.,.,.,DiningChair_WoodLog_East,Table1x2c_BlocksMarble_North,DiningChair_WoodLog_West,.,.,.,Wall_BlocksGranite,.,.,.,Wall_BlocksGranite,.,.,.,.,.,.,.,.,.,Wall_BlocksGranite,.,.,.,.,.,.,.,.,.,.</li>
                <li>.,.,.,.,.,.,.,.,.,.,.,.,.,Wall_BlocksGranite,BlocksGranite,Steel,.,.,.,.,WoodLog,WoodLog,.,Wall_BlocksGranite,.,.,.,.,.,.,.,.,.,.,.,.,.,.,.,.,.,.,.,Wall_BlocksGranite,.,.,.,DiningChair_WoodLog_East,.,DiningChair_WoodLog_West,.,.,.,Wall_BlocksGranite,.,.,.,Wall_BlocksGranite,.,.,.,.,StandingLamp,.,.,.,.,Wall_BlocksGranite,.,.,.,.,.,.,.,.,.,.</li>
                <li>.,.,.,.,.,.,.,.,.,.,.,.,.,Wall_BlocksGranite,BlocksGranite,.,.,.,Steel,.,.,.,.,Wall_BlocksGranite,.,.,.,SolarGenerator,.,.,.,.,.,.,.,.,.,.,.,.,.,.,.,Wall_BlocksGranite,.,.,.,.,.,.,.,.,.,Wall_BlocksGranite,.,.,.,Wall_BlocksGranite,.,.,.,.,.,.,.,.,.,Wall_BlocksGranite,.,.,.,.,.,.,.,.,.,.</li>
                <li>.,.,.,.,.,.,.,.,.,.,.,.,.,Wall_BlocksGranite,BlocksGranite,.,Steel,.,.,.,.,.,.,Wall_BlocksGranite,.,.,.,.,.,.,.,.,.,.,.,.,.,.,.,.,.,.,.,Wall_BlocksGranite,.,.,.,.,.,.,.,.,.,Wall_BlocksGranite,.,.,.,Wall_BlocksGranite,.,.,.,.,.,.,.,.,.,Wall_BlocksGranite,.,.,.,.,.,.,.,.,.,.</li>
                <li>.,.,.,.,.,.,.,.,.,.,.,.,.,Wall_BlocksGranite,BlocksGranite,Steel,.,.,Steel,.,.,.,.,Wall_BlocksGranite,.,.,.,.,.,.,.,.,.,.,.,.,.,.,.,.,.,.,.,Wall_BlocksGranite,.,.,.,DiningChair_WoodLog_East,Table1x2c_BlocksMarble_North,DiningChair_WoodLog_West,.,.,.,Wall_BlocksGranite,.,.,.,Wall_BlocksGranite,.,TableButcher_WoodLog_North,.,.,.,.,.,ElectricStove_North,.,Wall_BlocksGranite,.,.,.,.,.,.,.,.,.,.</li>
                <li>.,.,.,.,.,.,.,.,.,.,.,.,.,Wall_BlocksGranite,BlocksGranite,.,.,Steel,Steel,.,.,.,.,Wall_BlocksGranite,.,.,.,.,.,.,.,.,.,.,.,.,.,.,.,.,.,.,.,Wall_BlocksGranite,.,.,.,DiningChair_WoodLog_East,.,DiningChair_WoodLog_West,.,.,.,Wall_BlocksGranite,HiddenConduit,HiddenConduit,HiddenConduit,Wall_BlocksGranite,Wall_BlocksGranite,Wall_BlocksGranite,Wall_BlocksGranite,Wall_BlocksGranite,Wall_BlocksGranite,Wall_BlocksGranite,Wall_BlocksGranite,Wall_BlocksGranite,Wall_BlocksGranite,Wall_BlocksGranite,.,.,.,.,.,.,.,.,.,.</li>
                <li>.,.,.,.,.,.,.,.,.,.,.,.,.,Wall_BlocksGranite,BlocksGranite,Steel,Steel,Steel,Steel,.,.,.,.,Wall_BlocksGranite,.,.,.,SolarGenerator,.,.,.,.,.,.,.,.,.,.,.,.,.,.,.,Wall_BlocksGranite,.,.,.,.,StandingLamp,.,.,.,.,Wall_BlocksGranite,.,.,.,.,.,.,.,.,.,.,.,.,.,.,.,.,.,.,.,.,.,.,.,.</li>
                <li>.,.,.,.,.,.,.,.,.,.,.,.,.,Wall_BlocksGranite,BlocksGranite,.,.,.,.,.,MealSurvivalPack,.,.,Wall_BlocksGranite,.,.,.,.,.,.,.,.,.,.,.,.,.,.,.,.,.,.,.,Wall_BlocksGranite,.,.,.,.,.,.,.,.,.,Wall_BlocksGranite,.,.,.,.,.,.,.,.,.,.,.,.,.,.,.,.,.,.,.,.,.,.,.,.</li>
                <li>.,.,.,.,.,.,.,.,.,.,.,.,.,Wall_BlocksGranite,BlocksGranite,.,.,.,.,.,.,.,.,Wall_BlocksGranite,.,.,.,.,.,.,.,.,.,.,.,.,.,.,.,.,.,.,.,Wall_BlocksGranite,.,.,.,.,.,.,.,.,.,Wall_BlocksGranite,.,.,.,.,.,.,.,.,.,.,.,.,.,.,.,.,.,.,.,.,.,.,.,.</li>
                <li>.,.,.,.,.,.,.,.,.,.,.,.,.,Wall_BlocksGranite,BlocksGranite,.,.,.,.,.,.,.,.,Wall_BlocksGranite,.,.,.,.,.,.,.,.,.,.,.,.,.,.,.,.,.,.,.,Wall_BlocksGranite,.,.,.,.,.,.,.,.,.,Wall_BlocksGranite,.,.,.,.,.,.,.,.,.,.,.,.,.,.,.,.,.,.,.,.,.,.,.,.</li>
                <li>.,.,.,.,.,.,.,.,.,.,.,.,.,Wall_BlocksGranite,BlocksGranite,.,.,.,.,.,.,BlocksGranite,.,Wall_BlocksGranite,.,.,.,SolarGenerator,.,.,.,.,.,.,.,.,.,.,.,.,.,.,.,Wall_BlocksGranite,.,.,.,.,BilliardsTable_BlocksLimestone_North,.,.,.,.,Wall_BlocksGranite,.,.,.,.,.,.,.,.,.,.,.,.,.,.,.,.,.,.,.,.,.,.,.,.</li>
                <li>.,.,.,.,.,.,.,.,.,.,.,.,.,Wall_BlocksGranite,BlocksGranite,.,.,.,.,.,.,.,.,Wall_BlocksGranite,.,.,.,.,.,.,.,.,.,.,.,.,.,.,.,.,.,.,.,Wall_BlocksGranite,.,.,.,.,.,.,.,.,.,Wall_BlocksGranite,.,.,.,.,.,.,.,.,.,.,.,.,.,.,.,.,.,.,.,.,.,.,.,.</li>
                <li>.,.,.,.,.,.,.,.,.,.,.,.,.,Wall_BlocksGranite,BlocksGranite,.,.,.,.,.,.,.,.,Wall_BlocksGranite,.,.,.,.,.,.,.,.,.,.,.,.,.,.,.,.,.,.,.,Wall_BlocksGranite,.,.,.,.,.,.,.,.,.,Wall_BlocksGranite,.,.,.,.,.,.,.,.,.,.,.,.,.,.,.,.,.,.,.,.,.,.,.,.</li>
                <li>.,.,.,.,.,.,.,.,.,.,.,.,.,Wall_BlocksGranite,BlocksGranite,.,.,.,.,.,.,.,.,Wall_BlocksGranite,.,.,.,.,.,.,.,.,.,.,.,.,.,.,.,.,.,.,.,Wall_BlocksGranite,.,.,.,.,.,.,.,.,.,Wall_BlocksGranite,.,.,.,.,.,.,.,.,.,.,.,.,.,.,.,.,.,.,.,.,.,.,.,.</li>
                <li>.,.,.,.,.,.,.,.,.,.,.,.,.,Wall_BlocksGranite,BlocksGranite,.,.,.,.,.,.,.,.,Wall_BlocksGranite,.,.,.,SolarGenerator,.,.,.,.,.,.,.,.,.,.,.,.,.,.,.,Wall_BlocksGranite,.,.,.,.,.,.,.,.,.,Wall_BlocksGranite,.,.,.,.,.,.,.,.,.,.,.,.,.,.,.,.,.,.,.,.,.,.,.,.</li>
                <li>.,.,.,.,.,.,.,.,.,.,.,.,.,Wall_BlocksGranite,Wall_BlocksGranite,Wall_BlocksGranite,Wall_BlocksGranite,Wall_BlocksGranite,Wall_BlocksGranite,Wall_BlocksGranite,Wall_BlocksGranite,Wall_BlocksGranite,Wall_BlocksGranite,Wall_BlocksGranite,.,.,.,.,.,.,.,.,.,.,.,.,.,.,.,.,.,.,.,Wall_BlocksGranite,Wall_BlocksGranite,Wall_BlocksGranite,Wall_BlocksGranite,Wall_BlocksGranite,Wall_BlocksGranite,Wall_BlocksGranite,Wall_BlocksGranite,Wall_BlocksGranite,Wall_BlocksGranite,Wall_BlocksGranite,.,.,.,.,.,.,.,.,.,.,.,.,.,.,.,.,.,.,.,.,.,.,.,.</li>
                <li>.,.,.,.,.,.,.,.,.,.,.,.,.,.,.,.,.,.,.,.,.,.,.,.,.,.,.,.,.,.,.,.,.,.,.,.,.,.,.,.,.,.,.,.,.,.,.,.,.,.,.,.,.,.,.,.,.,.,.,.,.,.,.,.,.,.,.,.,.,.,.,.,.,.,.,.,.,.</li>
                <li>.,.,.,.,.,.,.,.,.,.,.,.,.,.,.,.,.,.,.,.,.,.,.,.,.,.,.,.,.,.,.,.,.,.,.,.,.,.,.,.,.,.,.,.,.,.,.,.,.,.,.,.,.,.,.,.,.,.,.,.,.,.,.,.,.,.,.,.,.,.,.,.,.,.,.,.,.,.</li>
                <li>.,.,.,.,.,.,.,.,.,.,.,.,.,.,.,.,.,.,.,.,.,.,.,.,.,.,.,.,.,.,.,.,.,.,.,.,.,.,.,.,.,.,.,.,.,.,.,.,.,.,.,.,.,.,.,.,.,.,.,.,.,.,.,.,.,.,.,.,.,.,.,.,.,.,.,.,.,.</li>
                <li>.,.,.,.,.,.,.,.,.,.,.,.,.,.,.,.,.,.,.,.,.,.,.,.,.,.,.,.,.,.,.,.,.,.,.,.,.,.,.,.,.,.,.,.,.,.,.,.,.,.,.,.,.,.,.,.,.,.,.,.,.,.,.,.,.,.,.,.,.,.,.,.,.,.,.,.,.,.</li>
                <li>.,.,.,.,.,.,.,.,.,.,.,.,.,.,.,.,.,.,.,.,.,.,.,.,.,.,.,.,.,.,.,.,.,.,.,.,.,.,.,.,.,.,.,.,.,.,.,.,.,.,.,.,.,.,.,.,.,.,.,.,.,.,.,.,.,.,.,.,.,.,.,.,.,.,.,.,.,.</li>
                <li>.,.,.,.,.,.,.,.,.,.,.,.,.,.,.,.,.,.,.,.,.,.,.,.,.,.,.,.,.,.,.,.,.,.,.,.,.,.,.,.,.,.,.,.,.,.,.,.,.,.,.,.,.,.,.,.,.,.,.,.,.,.,.,.,.,.,.,.,.,.,.,.,.,.,.,.,.,.</li>
                <li>.,.,.,.,.,.,.,.,.,.,.,.,.,.,.,.,.,.,.,.,.,.,.,.,.,.,.,.,.,.,.,.,.,.,.,.,.,.,.,.,.,.,.,.,.,.,.,.,.,.,.,.,.,.,.,.,.,.,.,.,.,.,.,.,.,.,.,.,.,.,.,.,.,.,.,.,.,.</li>
                <li>.,.,.,.,.,.,.,.,.,.,.,.,.,.,.,.,.,.,.,.,.,.,.,.,.,.,.,.,.,.,.,.,.,.,.,.,.,.,.,.,.,.,.,.,.,.,.,.,.,.,.,.,.,.,.,.,.,.,.,.,.,.,.,.,.,.,.,.,.,.,.,.,.,.,.,.,.,.</li>
                <li>.,.,.,.,.,.,.,.,.,.,.,.,.,.,.,.,.,.,.,.,.,.,.,.,.,.,.,.,.,.,.,.,.,.,.,.,.,.,.,.,.,.,.,.,.,.,.,.,.,.,.,.,.,.,.,.,.,.,.,.,.,.,.,.,.,.,.,.,.,.,.,.,.,.,.,.,.,.</li>
                <li>.,.,.,.,.,.,.,.,.,.,.,.,.,.,.,.,.,.,.,.,.,.,.,.,.,.,.,.,.,.,.,.,.,.,.,.,.,.,.,.,.,.,.,.,.,.,.,.,.,.,.,.,.,.,.,.,.,.,.,.,.,.,.,.,.,.,.,.,.,.,.,.,.,.,.,.,.,.</li>
            </li>
            <li>
                <li>.,.,.,.,.,.,.,.,.,.,.,.,.,.,.,.,.,.,.,.,.,.,.,.,.,.,.,.,.,.,.,.,.,.,.,.,.,.,.,.,.,.,.,.,.,.,.,.,.,.,.,.,.,.,.,.,.,.,.,.,.,.,.,.,.,.,.,.,.,.,.,.,.,.,.,.,.,.</li>
                <li>.,.,.,.,.,.,.,.,.,.,.,.,.,.,.,.,.,.,.,.,.,.,.,.,.,.,.,.,.,.,.,.,.,.,.,.,.,.,.,.,.,.,.,.,.,.,.,.,.,.,.,.,.,.,.,.,.,.,.,.,.,.,.,.,.,.,.,.,.,.,.,.,.,.,.,.,.,.</li>
                <li>.,.,.,.,.,.,.,.,.,.,.,.,.,.,.,.,.,.,.,.,.,.,.,.,.,.,.,.,.,.,.,.,.,.,.,.,.,.,.,.,.,.,.,.,.,.,.,.,.,.,.,.,.,.,.,.,.,.,.,.,.,.,.,.,.,.,.,.,.,.,.,.,.,.,.,.,.,.</li>
                <li>.,.,.,.,.,.,.,.,.,.,.,.,.,.,.,.,.,.,.,.,.,.,.,.,.,.,.,.,.,.,.,.,.,.,.,.,.,.,.,.,.,.,.,.,.,.,.,.,.,.,.,.,.,.,.,.,.,.,.,.,.,.,.,.,.,.,.,.,.,.,.,.,.,.,.,.,.,.</li>
                <li>.,.,.,.,.,.,.,.,.,.,.,.,.,.,.,.,.,.,.,.,.,.,.,.,.,.,.,.,.,.,.,.,.,.,.,.,.,.,.,.,.,.,.,.,.,.,.,.,.,.,.,.,.,.,.,.,.,.,.,.,.,.,.,.,.,.,.,.,.,.,.,.,.,.,.,.,.,.</li>
                <li>.,.,.,.,.,.,.,.,.,.,.,.,.,.,.,.,HiddenConduit,.,.,.,HiddenConduit,.,.,.,.,.,.,.,.,.,.,.,.,.,.,.,.,.,.,.,.,.,.,HiddenConduit,.,.,.,.,.,.,.,.,.,.,.,.,.,.,.,.,.,.,.,.,.,HiddenConduit,.,.,.,.,.,.,.,.,.,.,.,.</li>
                <li>.,.,.,.,.,.,.,.,.,.,.,.,.,.,.,.,HiddenConduit,.,.,.,HiddenConduit,.,.,.,.,.,.,.,.,.,.,.,.,.,.,.,.,.,.,.,.,.,.,HiddenConduit,.,.,.,.,.,.,.,.,.,.,.,.,.,.,.,.,.,.,.,.,.,.,.,.,.,.,.,.,.,.,.,.,.,.</li>
                <li>.,.,.,.,.,.,.,.,.,.,.,.,.,.,.,.,HiddenConduit,.,.,.,HiddenConduit,.,.,.,.,.,.,.,.,.,.,.,.,.,.,.,.,.,.,.,.,.,.,HiddenConduit,.,.,.,.,.,.,.,.,.,.,.,.,.,.,.,.,.,.,.,.,.,.,.,.,.,.,.,.,.,.,.,.,.,.</li>
                <li>.,.,.,.,.,.,.,.,.,.,.,.,.,.,.,.,HiddenConduit,.,.,.,HiddenConduit,.,.,.,.,.,.,.,.,.,.,.,.,.,.,.,.,.,.,.,.,.,.,HiddenConduit,.,.,.,.,.,.,.,.,.,.,.,.,.,.,.,.,.,.,.,.,.,.,.,.,.,.,.,.,.,.,.,.,.,.</li>
                <li>.,.,.,.,.,.,.,.,.,.,.,.,.,.,.,.,HiddenConduit,.,.,.,HiddenConduit,.,.,.,.,.,.,.,.,.,.,.,.,.,.,.,.,.,.,.,.,.,.,HiddenConduit,.,.,.,.,.,.,.,.,.,.,.,.,.,.,.,.,.,.,.,.,.,HiddenConduit,.,.,.,.,.,.,.,.,.,.,.,.</li>
                <li>.,.,.,.,.,.,.,.,.,.,.,.,.,.,.,.,HiddenConduit,.,.,.,HiddenConduit,.,.,.,.,.,.,.,.,.,.,.,.,.,.,.,.,.,.,.,.,.,.,HiddenConduit,.,.,.,.,.,.,.,.,.,.,.,.,.,.,.,.,.,.,.,.,.,.,.,.,.,.,.,.,.,.,.,.,.,.</li>
                <li>.,.,.,.,.,.,.,.,.,.,.,.,.,.,.,.,HiddenConduit,.,.,.,HiddenConduit,.,.,.,.,.,.,.,.,.,.,.,.,.,.,.,.,.,.,.,.,.,.,HiddenConduit,.,.,.,.,.,.,.,.,.,.,.,.,.,.,.,.,.,.,.,.,.,.,.,.,.,.,.,.,.,.,.,.,.,.</li>
                <li>.,.,.,.,.,.,.,.,.,.,.,.,.,.,.,.,HiddenConduit,.,.,.,HiddenConduit,.,.,.,.,.,.,.,.,.,.,.,.,.,.,.,.,.,.,.,.,.,.,HiddenConduit,.,.,.,.,.,.,.,.,.,.,.,.,.,.,.,.,.,.,.,.,.,.,.,.,.,.,.,.,.,.,.,.,.,.</li>
                <li>.,.,.,.,.,.,.,.,.,.,.,.,.,.,.,.,HiddenConduit,.,.,.,HiddenConduit,.,.,.,.,.,.,.,.,.,.,.,.,.,.,.,.,.,.,.,.,.,.,HiddenConduit,.,.,.,.,.,.,.,.,.,.,.,.,.,.,.,.,.,.,.,.,.,.,.,.,.,.,.,.,.,.,.,.,.,.</li>
                <li>.,.,.,.,.,.,.,.,.,.,.,.,.,.,.,.,HiddenConduit,.,.,.,HiddenConduit,.,.,.,.,.,.,.,.,.,.,.,.,.,.,.,.,.,.,.,.,.,.,HiddenConduit,HiddenConduit,HiddenConduit,HiddenConduit,HiddenConduit,HiddenConduit,HiddenConduit,HiddenConduit,HiddenConduit,HiddenConduit,HiddenConduit,.,.,.,HiddenConduit,.,.,.,.,.,.,.,.,.,.,.,.,.,.,.,.,.,.,.,.</li>
                <li>.,.,.,.,.,.,.,.,.,.,.,.,.,.,.,.,HiddenConduit,.,.,.,HiddenConduit,.,.,.,.,.,.,.,.,.,.,.,.,.,.,.,.,.,.,.,.,.,.,HiddenConduit,.,.,.,.,.,.,.,.,.,.,.,.,.,HiddenConduit,HiddenConduit,HiddenConduit,HiddenConduit,HiddenConduit,HiddenConduit,HiddenConduit,HiddenConduit,HiddenConduit,HiddenConduit,HiddenConduit,HiddenConduit,HiddenConduit,HiddenConduit,HiddenConduit,HiddenConduit,HiddenConduit,HiddenConduit,HiddenConduit,.,.</li>
                <li>.,.,.,.,.,.,.,.,.,.,.,.,.,.,.,.,HiddenConduit,.,.,.,HiddenConduit,.,.,.,.,.,.,.,.,.,.,.,.,.,.,.,.,.,.,.,.,.,.,HiddenConduit,.,.,.,.,.,.,.,.,.,.,.,.,.,.,.,.,.,.,.,.,.,.,.,.,.,.,.,.,.,.,.,.,.,.</li>
                <li>.,.,.,.,.,.,.,.,.,.,.,.,.,.,.,.,HiddenConduit,.,.,.,HiddenConduit,.,.,.,.,.,.,.,.,.,.,.,.,.,.,.,.,.,.,.,.,.,.,HiddenConduit,.,.,.,.,.,.,.,.,.,.,.,.,.,.,.,.,.,.,.,.,.,.,.,.,.,.,.,.,.,.,.,.,.,.</li>
                <li>.,.,.,.,.,.,.,.,.,.,.,.,.,.,.,.,HiddenConduit,.,.,.,HiddenConduit,.,.,.,.,.,.,.,.,.,.,.,.,.,.,.,.,.,.,.,.,.,.,HiddenConduit,.,.,.,.,.,.,.,.,.,.,.,.,.,.,.,.,.,.,.,.,.,.,.,.,.,.,.,.,.,.,.,.,.,.</li>
                <li>.,.,.,.,.,.,.,.,.,.,.,.,.,.,.,.,HiddenConduit,.,.,.,HiddenConduit,.,.,.,.,.,.,.,.,.,.,.,.,.,.,.,.,.,.,.,.,.,.,HiddenConduit,.,.,.,.,.,.,.,.,.,.,.,.,.,.,.,.,.,.,.,.,.,.,.,.,.,.,.,.,.,.,.,.,.,.</li>
                <li>.,.,.,.,.,.,.,.,.,.,.,.,.,.,.,.,HiddenConduit,.,.,.,HiddenConduit,.,.,.,.,.,.,.,.,.,.,.,.,.,.,.,.,.,.,.,.,.,.,HiddenConduit,.,.,.,.,.,.,.,.,.,.,.,.,.,.,.,.,.,.,.,.,.,.,.,.,.,.,.,.,.,.,.,.,.,.</li>
                <li>.,.,.,.,.,.,.,.,.,.,.,.,.,.,.,.,HiddenConduit,.,.,.,HiddenConduit,.,.,.,.,.,.,.,.,.,.,.,.,.,.,.,.,.,.,.,.,.,.,HiddenConduit,.,.,.,.,.,.,.,.,.,.,.,.,.,.,.,.,.,.,.,.,.,.,.,.,.,.,.,.,.,.,.,.,.,.</li>
                <li>.,.,.,.,.,.,.,.,.,.,.,.,.,.,.,.,HiddenConduit,.,.,.,HiddenConduit,.,.,.,.,.,.,.,.,.,.,.,.,.,.,.,.,.,.,.,.,.,.,HiddenConduit,.,.,.,.,.,.,.,.,.,.,.,.,.,.,.,.,.,.,.,.,.,.,.,.,.,.,.,.,.,.,.,.,.,.</li>
                <li>.,.,.,.,.,.,.,.,.,.,.,.,.,.,.,.,HiddenConduit,.,.,.,HiddenConduit,.,.,.,.,.,.,.,.,.,.,.,.,.,.,.,.,.,.,.,.,.,.,HiddenConduit,.,.,.,.,.,.,.,.,.,.,.,.,.,.,.,.,.,.,.,.,.,.,.,.,.,.,.,.,.,.,.,.,.,.</li>
                <li>.,.,.,.,.,.,.,.,.,.,.,.,.,.,.,.,.,.,.,.,.,.,.,.,.,.,.,.,.,.,.,.,.,.,.,.,.,.,.,.,.,.,.,.,.,.,.,.,.,.,.,.,.,.,.,.,.,.,.,.,.,.,.,.,.,.,.,.,.,.,.,.,.,.,.,.,.,.</li>
                <li>.,.,.,.,.,.,.,.,.,.,.,.,.,.,.,.,.,.,.,.,.,.,.,.,.,.,.,.,.,.,.,.,.,.,.,.,.,.,.,.,.,.,.,.,.,.,.,.,.,.,.,.,.,.,.,.,.,.,.,.,.,.,.,.,.,.,.,.,.,.,.,.,.,.,.,.,.,.</li>
                <li>.,.,.,.,.,.,.,.,.,.,.,.,.,.,.,.,.,.,.,.,.,.,.,.,.,.,.,.,.,.,.,.,.,.,.,.,.,.,.,.,.,.,.,.,.,.,.,.,.,.,.,.,.,.,.,.,.,.,.,.,.,.,.,.,.,.,.,.,.,.,.,.,.,.,.,.,.,.</li>
                <li>.,.,.,.,.,.,.,.,.,.,.,.,.,.,.,.,.,.,.,.,.,.,.,.,.,.,.,.,.,.,.,.,.,.,.,.,.,.,.,.,.,.,.,.,.,.,.,.,.,.,.,.,.,.,.,.,.,.,.,.,.,.,.,.,.,.,.,.,.,.,.,.,.,.,.,.,.,.</li>
                <li>.,.,.,.,.,.,.,.,.,.,.,.,.,.,.,.,.,.,.,.,.,.,.,.,.,.,.,.,.,.,.,.,.,.,.,.,.,.,.,.,.,.,.,.,.,.,.,.,.,.,.,.,.,.,.,.,.,.,.,.,.,.,.,.,.,.,.,.,.,.,.,.,.,.,.,.,.,.</li>
                <li>.,.,.,.,.,.,.,.,.,.,.,.,.,.,.,.,.,.,.,.,.,.,.,.,.,.,.,.,.,.,.,.,.,.,.,.,.,.,.,.,.,.,.,.,.,.,.,.,.,.,.,.,.,.,.,.,.,.,.,.,.,.,.,.,.,.,.,.,.,.,.,.,.,.,.,.,.,.</li>
                <li>.,.,.,.,.,.,.,.,.,.,.,.,.,.,.,.,.,.,.,.,.,.,.,.,.,.,.,.,.,.,.,.,.,.,.,.,.,.,.,.,.,.,.,.,.,.,.,.,.,.,.,.,.,.,.,.,.,.,.,.,.,.,.,.,.,.,.,.,.,.,.,.,.,.,.,.,.,.</li>
                <li>.,.,.,.,.,.,.,.,.,.,.,.,.,HiddenConduit,HiddenConduit,HiddenConduit,HiddenConduit,HiddenConduit,HiddenConduit,HiddenConduit,HiddenConduit,HiddenConduit,HiddenConduit,HiddenConduit,.,.,.,.,.,.,.,.,.,.,.,.,.,.,.,.,.,.,.,HiddenConduit,HiddenConduit,HiddenConduit,HiddenConduit,HiddenConduit,HiddenConduit,HiddenConduit,HiddenConduit,HiddenConduit,HiddenConduit,HiddenConduit,.,.,.,HiddenConduit,HiddenConduit,HiddenConduit,HiddenConduit,HiddenConduit,HiddenConduit,HiddenConduit,HiddenConduit,HiddenConduit,HiddenConduit,HiddenConduit,.,.,.,.,.,.,.,.,.,.</li>
                <li>.,.,.,.,.,.,.,.,.,.,.,.,.,HiddenConduit,.,.,.,.,.,.,.,.,.,.,.,.,.,.,.,.,.,.,.,.,.,.,.,.,.,.,.,.,.,.,.,.,.,.,.,.,.,.,.,HiddenConduit,.,.,.,.,.,.,.,.,.,.,.,.,.,.,.,.,.,.,.,.,.,.,.,.</li>
                <li>.,.,.,.,.,.,.,.,.,.,.,.,.,HiddenConduit,ElectricSmelter_West,.,.,.,.,.,.,.,.,.,.,.,.,.,.,.,.,.,.,.,.,.,.,.,.,.,.,.,.,.,.,.,.,.,.,.,.,.,.,HiddenConduit,.,.,.,.,.,.,.,.,.,.,.,.,.,.,.,.,.,.,.,.,.,.,.,.</li>
                <li>.,.,.,.,.,.,.,.,.,.,.,.,.,HiddenConduit,.,.,.,.,.,.,.,.,.,.,.,.,.,.,.,.,.,.,.,.,.,.,.,.,.,.,.,.,.,.,.,.,.,.,.,.,.,.,.,HiddenConduit,.,.,.,.,.,.,.,.,.,.,.,.,.,.,.,.,.,.,.,.,.,.,.,.</li>
                <li>.,.,.,.,.,.,.,.,.,.,.,.,.,HiddenConduit,.,.,.,.,.,.,.,.,.,.,.,.,.,.,.,.,.,.,.,.,.,.,.,.,.,.,.,.,.,.,.,.,.,.,.,.,.,.,.,HiddenConduit,.,.,.,.,.,.,.,.,.,.,.,.,.,.,.,.,.,.,.,.,.,.,.,.</li>
                <li>.,.,.,.,.,.,.,.,.,.,.,.,.,HiddenConduit,ElectricTailoringBench_Steel_West,.,.,.,.,.,.,.,.,.,.,.,.,.,.,.,.,.,.,.,.,.,.,.,.,.,.,.,.,.,.,.,.,.,.,.,.,.,.,HiddenConduit,.,.,.,.,.,.,.,.,.,.,.,.,.,.,.,.,.,.,.,.,.,.,.,.</li>
                <li>.,.,.,.,.,.,.,.,.,.,.,.,.,HiddenConduit,.,.,.,.,.,.,.,.,.,.,.,.,.,.,.,.,.,.,.,.,.,.,.,.,.,.,.,.,.,.,.,.,.,.,.,.,.,.,.,HiddenConduit,.,.,.,.,.,.,.,.,.,.,.,.,.,.,.,.,.,.,.,.,.,.,.,.</li>
                <li>.,.,.,.,.,.,.,.,.,.,.,.,.,HiddenConduit,.,.,.,.,StandingLamp,.,.,.,.,.,.,.,.,.,.,.,.,.,.,.,.,.,.,.,.,.,.,.,.,.,.,.,.,.,.,.,.,.,.,HiddenConduit,.,.,.,.,.,.,.,.,.,.,.,.,.,.,.,.,.,.,.,.,.,.,.,.</li>
                <li>.,.,.,.,.,.,.,.,.,.,.,.,.,HiddenConduit,ElectricSmithy_West,.,.,.,.,.,.,.,.,.,.,.,.,.,.,.,.,.,.,.,.,.,.,.,.,.,.,.,.,.,.,.,.,.,.,.,.,.,.,HiddenConduit,.,.,.,HiddenConduit,HiddenConduit,HiddenConduit,HiddenConduit,HiddenConduit,HiddenConduit,HiddenConduit,HiddenConduit,HiddenConduit,HiddenConduit,HiddenConduit,.,.,.,.,.,.,.,.,.,.</li>
                <li>.,.,.,.,.,.,.,.,.,.,.,.,.,HiddenConduit,.,.,.,.,.,.,.,.,.,.,.,.,.,.,.,.,.,.,.,.,.,.,.,.,.,.,.,.,.,.,.,.,.,.,.,.,.,.,.,HiddenConduit,.,.,.,.,.,.,.,.,.,.,.,.,.,.,.,.,.,.,.,.,.,.,.,.</li>
                <li>.,.,.,.,.,.,.,.,.,.,.,.,.,HiddenConduit,.,.,.,.,.,.,.,.,.,.,.,.,.,.,.,.,.,.,.,.,.,.,.,.,.,.,.,.,.,.,.,.,.,.,.,.,.,.,.,HiddenConduit,.,.,.,.,.,.,.,.,.,.,.,.,.,.,.,.,.,.,.,.,.,.,.,.</li>
                <li>.,.,.,.,.,.,.,.,.,.,.,.,.,HiddenConduit,TableMachining_West,.,.,.,.,.,.,.,.,.,.,.,.,.,.,.,.,.,.,.,.,.,.,.,.,.,.,.,.,.,.,.,.,.,.,.,.,.,.,HiddenConduit,.,.,.,.,.,.,.,.,.,.,.,.,.,.,.,.,.,.,.,.,.,.,.,.</li>
                <li>.,.,.,.,.,.,.,.,.,.,.,.,.,HiddenConduit,.,.,.,.,.,.,.,.,.,.,.,.,.,.,.,.,.,.,.,.,.,.,.,.,.,.,.,.,.,.,.,.,.,.,.,.,.,.,.,HiddenConduit,.,.,.,.,.,.,.,.,.,.,.,.,.,.,.,.,.,.,.,.,.,.,.,.</li>
                <li>.,.,.,.,.,.,.,.,.,.,.,.,.,HiddenConduit,.,.,.,.,.,.,.,.,.,.,.,.,.,.,.,.,.,.,.,.,.,.,.,.,.,.,.,.,.,.,.,.,.,.,.,.,.,.,.,HiddenConduit,.,.,.,.,.,.,.,.,.,.,.,.,.,.,.,.,.,.,.,.,.,.,.,.</li>
                <li>.,.,.,.,.,.,.,.,.,.,.,.,.,HiddenConduit,.,.,.,.,.,.,.,.,.,.,.,.,.,.,.,.,.,.,.,.,.,.,.,.,.,.,.,.,.,.,.,.,.,.,.,.,.,.,.,HiddenConduit,.,.,.,.,.,.,.,.,.,.,.,.,.,.,.,.,.,.,.,.,.,.,.,.</li>
                <li>.,.,.,.,.,.,.,.,.,.,.,.,.,.,.,.,.,.,.,.,.,.,.,.,.,.,.,.,.,.,.,.,.,.,.,.,.,.,.,.,.,.,.,.,.,.,.,.,.,.,.,.,.,HiddenConduit,.,.,.,.,.,.,.,.,.,.,.,.,.,.,.,.,.,.,.,.,.,.,.,.</li>
                <li>.,.,.,.,.,.,.,.,.,.,.,.,.,.,.,.,.,.,.,.,.,.,.,.,.,.,.,.,.,.,.,.,.,.,.,.,.,.,.,.,.,.,.,.,.,.,.,.,.,.,.,.,.,HiddenConduit,.,.,.,.,.,.,.,.,.,.,.,.,.,.,.,.,.,.,.,.,.,.,.,.</li>
                <li>.,.,.,.,.,.,.,.,.,.,.,.,.,.,.,.,.,.,.,.,.,.,.,.,.,.,.,.,.,.,.,.,.,.,.,.,.,.,.,.,.,.,.,.,.,.,.,.,.,.,.,.,.,HiddenConduit,.,.,.,.,.,.,.,.,.,.,.,.,.,.,.,.,.,.,.,.,.,.,.,.</li>
                <li>.,.,.,.,.,.,.,.,.,.,.,.,.,.,.,.,.,.,.,.,.,.,.,.,.,.,.,.,.,.,.,.,.,.,.,.,.,.,.,.,.,.,.,.,.,.,.,.,.,.,.,.,.,.,.,.,.,.,.,.,.,.,.,.,.,.,.,.,.,.,.,.,.,.,.,.,.,.</li>
                <li>.,.,.,.,.,.,.,.,.,.,.,.,.,.,.,.,.,.,.,.,.,.,.,.,.,.,.,.,.,.,.,.,.,.,.,.,.,.,.,.,.,.,.,.,.,.,.,.,.,.,.,.,.,.,.,.,.,.,.,.,.,.,.,.,.,.,.,.,.,.,.,.,.,.,.,.,.,.</li>
                <li>.,.,.,.,.,.,.,.,.,.,.,.,.,.,.,.,.,.,.,.,.,.,.,.,.,.,.,.,.,.,.,.,.,.,.,.,.,.,.,.,.,.,.,.,.,.,.,.,.,.,.,.,.,.,.,.,.,.,.,.,.,.,.,.,.,.,.,.,.,.,.,.,.,.,.,.,.,.</li>
                <li>.,.,.,.,.,.,.,.,.,.,.,.,.,.,.,.,.,.,.,.,.,.,.,.,.,.,.,.,.,.,.,.,.,.,.,.,.,.,.,.,.,.,.,.,.,.,.,.,.,.,.,.,.,.,.,.,.,.,.,.,.,.,.,.,.,.,.,.,.,.,.,.,.,.,.,.,.,.</li>
                <li>.,.,.,.,.,.,.,.,.,.,.,.,.,.,.,.,.,.,.,.,.,.,.,.,.,.,.,.,.,.,.,.,.,.,.,.,.,.,.,.,.,.,.,.,.,.,.,.,.,.,.,.,.,.,.,.,.,.,.,.,.,.,.,.,.,.,.,.,.,.,.,.,.,.,.,.,.,.</li>
                <li>.,.,.,.,.,.,.,.,.,.,.,.,.,.,.,.,.,.,.,.,.,.,.,.,.,.,.,.,.,.,.,.,.,.,.,.,.,.,.,.,.,.,.,.,.,.,.,.,.,.,.,.,.,.,.,.,.,.,.,.,.,.,.,.,.,.,.,.,.,.,.,.,.,.,.,.,.,.</li>
                <li>.,.,.,.,.,.,.,.,.,.,.,.,.,.,.,.,.,.,.,.,.,.,.,.,.,.,.,.,.,.,.,.,.,.,.,.,.,.,.,.,.,.,.,.,.,.,.,.,.,.,.,.,.,.,.,.,.,.,.,.,.,.,.,.,.,.,.,.,.,.,.,.,.,.,.,.,.,.</li>
                <li>.,.,.,.,.,.,.,.,.,.,.,.,.,.,.,.,.,.,.,.,.,.,.,.,.,.,.,.,.,.,.,.,.,.,.,.,.,.,.,.,.,.,.,.,.,.,.,.,.,.,.,.,.,.,.,.,.,.,.,.,.,.,.,.,.,.,.,.,.,.,.,.,.,.,.,.,.,.</li>
                <li>.,.,.,.,.,.,.,.,.,.,.,.,.,.,.,.,.,.,.,.,.,.,.,.,.,.,.,.,.,.,.,.,.,.,.,.,.,.,.,.,.,.,.,.,.,.,.,.,.,.,.,.,.,.,.,.,.,.,.,.,.,.,.,.,.,.,.,.,.,.,.,.,.,.,.,.,.,.</li>
                <li>.,.,.,.,.,.,.,.,.,.,.,.,.,.,.,.,.,.,.,.,.,.,.,.,.,.,.,.,.,.,.,.,.,.,.,.,.,.,.,.,.,.,.,.,.,.,.,.,.,.,.,.,.,.,.,.,.,.,.,.,.,.,.,.,.,.,.,.,.,.,.,.,.,.,.,.,.,.</li>
                <li>.,.,.,.,.,.,.,.,.,.,.,.,.,.,.,.,.,.,.,.,.,.,.,.,.,.,.,.,.,.,.,.,.,.,.,.,.,.,.,.,.,.,.,.,.,.,.,.,.,.,.,.,.,.,.,.,.,.,.,.,.,.,.,.,.,.,.,.,.,.,.,.,.,.,.,.,.,.</li>
            </li>
        </layouts>
        <roofGrid>
            <li>.,.,.,.,.,.,.,.,.,.,.,.,.,.,.,.,.,.,.,.,.,.,.,.,.,.,.,.,.,.,.,.,.,.,.,.,.,.,.,.,.,.,.,.,.,.,.,.,.,.,.,.,.,.,.,.,.,.,.,.,.,.,.,.,.,.,.,.,.,.,.,.,.,.,.,.,.,.</li>
            <li>.,.,.,.,.,.,.,.,.,.,.,.,.,.,.,.,.,.,.,.,.,.,.,.,.,.,.,.,.,.,.,.,.,.,.,.,.,.,.,.,.,.,.,.,.,.,.,.,.,.,.,.,.,.,.,.,.,.,.,.,.,.,.,.,.,.,.,.,.,.,.,.,.,.,.,.,.,.</li>
            <li>.,.,.,.,.,.,.,.,.,.,.,.,.,.,.,.,.,.,.,.,.,.,.,.,.,.,.,.,.,.,.,.,.,.,.,.,.,.,.,.,.,.,.,.,.,.,.,.,.,.,.,.,.,.,.,.,.,.,.,.,.,.,.,.,.,.,.,.,.,.,.,.,.,.,.,.,.,.</li>
            <li>.,.,.,.,.,.,.,.,.,.,.,.,.,.,.,.,.,.,.,.,.,.,.,.,.,.,.,.,.,.,.,.,.,.,.,.,.,.,.,.,.,.,.,.,.,.,.,.,.,.,.,.,.,.,.,.,.,.,.,.,.,.,.,.,.,.,.,.,.,.,.,.,.,.,.,.,.,.</li>
            <li>.,.,.,.,.,.,.,.,.,.,.,.,.,.,.,.,.,.,.,.,.,.,.,.,.,.,.,.,.,.,.,.,.,.,.,.,.,.,.,.,.,.,.,.,.,.,.,.,.,.,.,.,.,.,.,.,.,.,.,.,.,.,.,.,.,.,.,.,.,.,.,.,.,.,.,.,.,.</li>
            <li>.,.,.,.,.,.,.,.,.,.,.,.,.,.,.,.,.,.,.,.,.,.,.,.,.,.,.,.,.,.,.,.,.,.,.,.,.,.,.,.,.,.,.,1,1,1,1,1,1,1,1,1,.,.,.,.,.,.,.,.,.,.,.,.,1,1,1,1,1,1,1,1,1,1,1,1,.,.</li>
            <li>.,.,.,.,.,.,.,.,.,.,.,.,.,.,.,.,.,.,.,.,.,.,.,.,.,.,.,.,.,.,.,.,.,.,.,.,.,.,.,.,.,.,.,1,1,1,1,1,1,1,1,1,.,.,.,.,.,.,.,.,.,.,.,.,1,1,1,1,1,1,1,1,1,1,1,1,.,.</li>
            <li>.,.,.,.,.,.,.,.,.,.,.,.,.,.,.,.,.,.,.,.,.,.,.,.,.,.,.,.,.,.,.,.,.,.,.,.,.,.,.,.,.,.,.,1,1,1,1,1,1,1,.,1,.,.,.,.,.,.,1,1,1,1,1,1,1,1,1,1,1,1,1,1,1,1,1,1,.,.</li>
            <li>.,.,.,.,.,.,.,.,.,.,.,.,.,.,.,.,.,.,.,.,.,.,.,.,.,.,.,.,.,.,.,.,.,.,.,.,.,.,.,.,.,.,.,.,1,1,1,1,1,.,.,.,.,.,.,.,.,.,1,1,1,1,1,1,1,1,1,1,1,1,1,1,1,1,1,1,.,.</li>
            <li>.,.,.,.,.,.,.,.,.,.,.,.,.,.,.,.,.,.,.,.,.,.,.,.,.,.,.,.,.,.,.,.,.,.,.,.,.,.,.,.,.,.,.,.,1,1,1,1,1,1,.,.,.,.,.,.,.,.,1,1,1,1,1,1,1,1,1,1,1,1,1,1,1,1,1,1,.,.</li>
            <li>.,.,.,.,.,.,.,.,.,.,.,.,.,.,.,.,.,.,.,.,.,.,.,.,.,.,.,.,.,.,.,.,.,.,.,.,.,.,.,.,.,.,.,.,1,1,1,1,1,.,.,.,.,.,.,.,.,.,1,1,1,1,1,1,1,1,1,1,1,1,1,1,1,1,1,1,.,.</li>
            <li>.,.,.,.,.,.,.,.,.,.,.,.,.,.,.,.,.,.,.,.,.,.,.,.,.,.,.,.,.,.,.,.,.,.,.,.,.,.,.,.,.,.,.,1,1,1,1,1,1,1,.,.,.,.,.,.,.,.,1,1,1,1,1,1,1,1,1,1,1,1,1,1,1,1,1,1,.,.</li>
            <li>.,.,.,.,.,.,.,.,.,.,.,.,.,.,.,.,.,.,.,.,.,.,.,.,.,.,.,.,.,.,.,.,.,.,.,.,.,.,.,.,.,.,.,1,1,1,1,1,1,.,.,.,.,.,.,.,.,.,1,1,1,1,1,1,1,1,1,1,1,1,1,1,1,1,1,1,.,.</li>
            <li>.,.,.,.,.,.,.,.,.,.,.,.,.,.,.,.,.,.,.,.,.,.,.,.,.,.,.,.,.,.,.,.,.,.,.,.,.,.,.,.,.,.,.,1,1,1,1,1,1,1,1,.,.,.,.,.,.,.,1,1,1,1,1,1,1,1,1,1,1,1,1,.,.,.,.,.,.,.</li>
            <li>.,.,.,.,.,.,.,.,.,.,.,.,.,.,.,.,.,.,.,.,.,.,.,.,.,.,.,.,.,.,.,.,.,.,.,.,.,.,.,.,.,.,.,1,1,1,1,.,1,1,1,1,1,.,.,.,.,.,1,1,1,1,1,1,1,1,1,1,1,1,1,.,.,.,.,.,.,.</li>
            <li>.,.,.,.,.,.,.,.,.,.,.,.,.,.,.,.,.,.,.,.,.,.,.,.,.,.,.,.,.,.,.,.,.,.,.,.,.,.,.,.,.,.,.,1,1,1,1,1,1,1,1,1,1,.,.,.,.,.,.,.,1,1,1,.,.,.,.,.,.,.,.,.,.,.,.,.,.,.</li>
            <li>.,.,.,.,.,.,.,.,.,.,.,.,.,.,.,.,.,.,.,.,.,.,.,.,.,.,.,.,.,.,.,.,.,.,.,.,.,.,.,.,.,.,.,1,1,1,1,1,1,1,1,1,1,.,.,.,.,.,.,.,.,.,.,.,.,.,.,.,.,.,.,.,.,.,.,.,.,.</li>
            <li>.,.,.,.,.,.,.,.,.,.,.,.,.,.,.,.,.,.,.,.,.,.,.,.,.,.,.,.,.,.,.,.,.,.,.,.,.,.,.,.,.,.,.,1,1,1,1,1,1,1,1,1,1,.,.,.,.,.,.,.,.,.,.,.,.,.,.,.,.,.,.,.,.,.,.,.,.,.</li>
            <li>.,.,.,.,.,.,.,.,.,.,.,.,.,.,.,.,.,.,.,.,.,.,.,.,.,.,.,.,.,.,.,.,.,.,.,.,.,.,.,.,.,.,.,1,1,1,1,1,1,1,1,1,1,.,.,.,.,.,.,.,.,.,.,.,.,.,.,.,.,.,.,.,.,.,.,.,.,.</li>
            <li>.,.,.,.,.,.,.,.,.,.,.,.,.,.,.,.,.,.,.,.,.,.,.,.,.,.,.,.,.,.,.,.,.,.,.,.,.,.,.,.,.,.,.,1,1,1,1,1,1,1,1,1,1,.,.,.,.,.,.,.,.,.,.,.,.,.,.,.,.,.,.,.,.,.,.,.,.,.</li>
            <li>.,.,.,.,.,.,.,.,.,.,.,.,.,.,.,.,.,.,.,.,.,.,.,.,.,.,.,.,.,.,.,.,.,.,.,.,.,.,.,.,.,.,.,1,1,1,1,1,1,1,1,1,1,.,.,.,.,.,.,.,.,.,.,.,.,.,.,.,.,.,.,.,.,.,.,.,.,.</li>
            <li>.,.,.,.,.,.,.,.,.,.,.,.,.,.,.,.,.,.,.,.,.,.,.,.,.,.,.,.,.,.,.,.,.,.,.,.,.,.,.,.,.,.,.,1,1,1,1,1,1,1,1,1,1,.,.,.,.,.,.,.,.,.,.,.,.,.,.,.,.,.,.,.,.,.,.,.,.,.</li>
            <li>.,.,.,.,.,.,.,.,.,.,.,.,.,.,.,.,.,.,.,.,.,.,.,.,.,.,.,.,.,.,.,.,.,.,.,.,.,.,.,.,.,.,.,1,1,1,1,1,1,1,1,1,.,.,.,.,.,.,.,.,.,.,.,.,.,.,.,.,.,.,.,.,.,.,.,.,.,.</li>
            <li>.,.,.,.,.,.,.,.,.,.,.,.,.,.,.,.,.,.,.,.,.,.,.,.,.,.,.,.,.,.,.,.,.,.,.,.,.,.,.,.,.,.,.,1,1,1,1,1,1,1,1,1,.,.,.,.,.,.,.,.,.,.,.,.,.,.,.,.,.,.,.,.,.,.,.,.,.,.</li>
            <li>.,.,.,.,.,.,.,.,.,.,.,.,.,.,.,.,.,.,.,.,.,.,.,.,.,.,.,.,.,.,.,.,.,.,.,.,.,.,.,.,.,.,.,.,.,.,.,.,.,.,.,.,.,.,.,.,.,.,.,.,.,.,.,.,.,.,.,.,.,.,.,.,.,.,.,.,.,.</li>
            <li>.,.,.,.,.,.,.,.,.,.,.,.,.,.,.,.,.,.,.,.,.,.,.,.,.,.,.,.,.,.,.,.,.,.,.,.,.,.,.,.,.,.,.,.,.,.,.,.,.,.,.,.,.,.,.,.,.,.,.,.,.,.,.,.,.,.,.,.,.,.,.,.,.,.,.,.,.,.</li>
            <li>.,.,.,.,.,.,.,.,.,.,.,.,.,.,.,.,.,.,.,.,.,.,.,.,.,.,.,.,.,.,.,.,.,.,.,.,.,.,.,.,.,.,.,.,.,.,.,.,.,.,.,.,.,.,.,.,.,.,.,.,.,.,.,.,.,.,.,.,.,.,.,.,.,.,.,.,.,.</li>
            <li>.,.,.,.,.,.,.,.,.,.,.,.,.,.,.,.,.,.,.,.,.,.,.,.,.,.,.,.,.,.,.,.,.,.,.,.,.,.,.,.,.,.,.,.,.,.,.,.,.,.,.,.,.,.,.,.,.,.,.,.,.,.,.,.,.,.,.,.,.,.,.,.,.,.,.,.,.,.</li>
            <li>.,.,.,.,.,.,.,.,.,.,.,.,.,.,.,.,.,.,.,.,.,.,.,.,.,.,.,.,.,.,.,.,.,.,.,.,.,.,.,.,.,.,.,.,.,.,.,.,.,.,.,.,.,.,.,.,.,.,.,.,.,.,.,.,.,.,.,.,.,.,.,.,.,.,.,.,.,.</li>
            <li>.,.,.,.,.,.,.,.,.,.,.,.,.,.,.,.,.,.,.,.,.,.,.,.,.,.,.,.,.,.,.,.,.,.,.,.,.,.,.,.,.,.,.,.,.,.,.,.,.,.,.,.,.,.,.,.,.,.,.,.,.,.,.,.,.,.,.,.,.,.,.,.,.,.,.,.,.,.</li>
            <li>.,.,.,.,.,.,.,.,.,.,.,.,.,.,.,.,.,.,.,.,.,.,.,.,.,.,.,.,.,.,.,.,.,.,.,.,.,.,.,.,.,.,.,.,.,.,.,.,.,.,.,.,.,.,.,.,.,.,.,.,.,.,.,.,.,.,.,.,.,.,.,.,.,.,.,.,.,.</li>
            <li>.,.,.,.,.,.,.,.,.,.,.,.,.,1,1,1,1,1,.,.,.,.,.,.,.,.,.,.,.,.,.,.,.,.,.,.,.,.,.,.,.,.,.,1,1,1,1,1,1,1,1,1,1,1,.,.,.,1,1,1,1,1,1,1,1,1,1,1,.,.,.,.,.,.,.,.,.,.</li>
            <li>.,.,.,.,.,.,.,.,.,.,.,.,.,1,1,1,1,1,1,1,.,.,.,.,.,.,.,.,.,.,.,.,.,.,.,.,.,.,.,.,.,.,.,1,1,1,1,1,1,1,1,1,1,1,.,.,.,1,1,1,1,1,1,1,1,1,1,1,.,.,.,.,.,.,.,.,.,.</li>
            <li>.,.,.,.,.,.,.,.,.,.,.,.,.,1,1,1,1,1,1,1,1,1,1,1,.,.,.,.,.,.,.,.,.,.,.,.,.,.,.,.,.,.,.,1,1,1,1,1,1,1,1,1,1,1,.,.,.,1,1,1,1,1,1,1,1,1,1,1,.,.,.,.,.,.,.,.,.,.</li>
            <li>.,.,.,.,.,.,.,.,.,.,.,.,.,1,1,1,1,1,1,1,1,1,1,1,.,.,.,.,.,.,.,.,.,.,.,.,.,.,.,.,.,.,.,1,1,1,1,1,1,1,1,1,1,1,.,.,.,1,1,1,1,1,1,1,1,1,1,1,.,.,.,.,.,.,.,.,.,.</li>
            <li>.,.,.,.,.,.,.,.,.,.,.,.,.,1,1,1,1,1,1,1,1,1,1,1,1,.,.,.,.,.,.,.,.,.,.,.,.,.,.,.,.,.,.,1,1,1,1,1,1,1,1,1,1,1,.,.,.,1,1,1,1,1,1,1,1,1,1,1,.,.,.,.,.,.,.,.,.,.</li>
            <li>.,.,.,.,.,.,.,.,.,.,.,.,.,1,1,1,1,1,1,1,1,1,1,1,1,.,.,.,.,.,.,.,.,.,.,.,.,.,.,.,.,.,.,1,1,1,1,1,1,1,1,1,1,1,.,.,.,1,1,1,1,1,1,1,1,1,1,1,.,.,.,.,.,.,.,.,.,.</li>
            <li>.,.,.,.,.,.,.,.,.,.,.,.,.,1,1,1,1,1,1,1,1,1,1,1,1,.,.,.,.,.,.,.,.,.,.,.,.,.,.,.,.,.,.,1,1,1,1,1,1,1,1,1,1,1,.,.,.,1,1,1,1,1,1,1,1,1,1,1,.,.,.,.,.,.,.,.,.,.</li>
            <li>.,.,.,.,.,.,.,.,.,.,.,.,.,.,1,1,1,1,1,1,1,1,1,1,1,.,.,.,.,.,.,.,.,.,.,.,.,.,.,.,.,.,.,1,1,1,1,1,1,1,1,1,1,1,.,.,.,1,1,1,1,1,1,1,1,1,1,1,.,.,.,.,.,.,.,.,.,.</li>
            <li>.,.,.,.,.,.,.,.,.,.,.,.,.,.,1,1,1,1,1,1,1,1,1,1,1,.,.,.,.,.,.,.,.,.,.,.,.,.,.,.,.,.,.,1,1,1,1,1,1,1,1,1,1,1,.,.,.,1,1,1,1,1,1,1,1,1,1,1,.,.,.,.,.,.,.,.,.,.</li>
            <li>.,.,.,.,.,.,.,.,.,.,.,.,.,.,1,.,1,.,.,.,1,1,1,1,1,.,.,.,.,.,.,.,.,.,.,.,.,.,.,.,.,.,.,1,1,1,1,1,1,1,1,1,1,1,.,.,.,.,.,.,.,.,.,.,.,.,.,.,.,.,.,.,.,.,.,.,.,.</li>
            <li>.,.,.,.,.,.,.,.,.,.,.,.,.,.,.,.,.,.,.,.,1,1,1,1,1,.,.,.,.,.,.,.,.,.,.,.,.,.,.,.,.,.,.,1,1,1,1,1,1,1,1,1,1,1,.,.,.,.,.,.,.,.,.,.,.,.,.,.,.,.,.,.,.,.,.,.,.,.</li>
            <li>.,.,.,.,.,.,.,.,.,.,.,.,.,.,.,.,.,.,.,.,1,1,1,1,1,.,.,.,.,.,.,.,.,.,.,.,.,.,.,.,.,.,.,1,1,1,1,1,1,1,1,1,1,1,.,.,.,.,.,.,.,.,.,.,.,.,.,.,.,.,.,.,.,.,.,.,.,.</li>
            <li>.,.,.,.,.,.,.,.,.,.,.,.,.,.,.,.,.,.,.,.,1,1,1,1,1,.,.,.,.,.,.,.,.,.,.,.,.,.,.,.,.,.,.,1,1,1,1,1,1,1,1,1,1,1,.,.,.,.,.,.,.,.,.,.,.,.,.,.,.,.,.,.,.,.,.,.,.,.</li>
            <li>.,.,.,.,.,.,.,.,.,.,.,.,.,.,.,.,1,.,1,.,1,1,1,1,1,.,.,.,.,.,.,.,.,.,.,.,.,.,.,.,.,.,.,1,1,1,1,1,1,1,1,1,1,1,.,.,.,.,.,.,.,.,.,.,.,.,.,.,.,.,.,.,.,.,.,.,.,.</li>
            <li>.,.,.,.,.,.,.,.,.,.,.,.,.,.,.,.,1,1,1,1,1,1,1,1,1,.,.,.,.,.,.,.,.,.,.,.,.,.,.,.,.,.,.,1,1,1,1,1,1,1,1,1,1,1,.,.,.,.,.,.,.,.,.,.,.,.,.,.,.,.,.,.,.,.,.,.,.,.</li>
            <li>.,.,.,.,.,.,.,.,.,.,.,.,.,.,.,.,1,1,1,1,1,1,1,1,1,.,.,.,.,.,.,.,.,.,.,.,.,.,.,.,.,.,.,1,1,1,1,1,1,1,1,1,1,1,.,.,.,.,.,.,.,.,.,.,.,.,.,.,.,.,.,.,.,.,.,.,.,.</li>
            <li>.,.,.,.,.,.,.,.,.,.,.,.,.,.,.,.,.,1,1,1,1,1,1,1,1,.,.,.,.,.,.,.,.,.,.,.,.,.,.,.,.,.,.,1,1,1,1,1,1,1,1,1,1,1,.,.,.,.,.,.,.,.,.,.,.,.,.,.,.,.,.,.,.,.,.,.,.,.</li>
            <li>.,.,.,.,.,.,.,.,.,.,.,.,.,.,.,.,.,1,1,1,1,1,1,1,1,.,.,.,.,.,.,.,.,.,.,.,.,.,.,.,.,.,.,1,1,1,1,1,1,1,1,1,1,1,.,.,.,.,.,.,.,.,.,.,.,.,.,.,.,.,.,.,.,.,.,.,.,.</li>
            <li>.,.,.,.,.,.,.,.,.,.,.,.,.,.,.,.,.,.,1,1,1,1,1,1,1,.,.,.,.,.,.,.,.,.,.,.,.,.,.,.,.,.,.,1,1,1,1,1,1,1,1,1,1,1,.,.,.,.,.,.,.,.,.,.,.,.,.,.,.,.,.,.,.,.,.,.,.,.</li>
            <li>.,.,.,.,.,.,.,.,.,.,.,.,.,.,.,.,.,.,.,.,.,.,.,.,.,.,.,.,.,.,.,.,.,.,.,.,.,.,.,.,.,.,.,.,.,.,.,.,.,.,.,.,.,.,.,.,.,.,.,.,.,.,.,.,.,.,.,.,.,.,.,.,.,.,.,.,.,.</li>
            <li>.,.,.,.,.,.,.,.,.,.,.,.,.,.,.,.,.,.,.,.,.,.,.,.,.,.,.,.,.,.,.,.,.,.,.,.,.,.,.,.,.,.,.,.,.,.,.,.,.,.,.,.,.,.,.,.,.,.,.,.,.,.,.,.,.,.,.,.,.,.,.,.,.,.,.,.,.,.</li>
            <li>.,.,.,.,.,.,.,.,.,.,.,.,.,.,.,.,.,.,.,.,.,.,.,.,.,.,.,.,.,.,.,.,.,.,.,.,.,.,.,.,.,.,.,.,.,.,.,.,.,.,.,.,.,.,.,.,.,.,.,.,.,.,.,.,.,.,.,.,.,.,.,.,.,.,.,.,.,.</li>
            <li>.,.,.,.,.,.,.,.,.,.,.,.,.,.,.,.,.,.,.,.,.,.,.,.,.,.,.,.,.,.,.,.,.,.,.,.,.,.,.,.,.,.,.,.,.,.,.,.,.,.,.,.,.,.,.,.,.,.,.,.,.,.,.,.,.,.,.,.,.,.,.,.,.,.,.,.,.,.</li>
            <li>.,.,.,.,.,.,.,.,.,.,.,.,.,.,.,.,.,.,.,.,.,.,.,.,.,.,.,.,.,.,.,.,.,.,.,.,.,.,.,.,.,.,.,.,.,.,.,.,.,.,.,.,.,.,.,.,.,.,.,.,.,.,.,.,.,.,.,.,.,.,.,.,.,.,.,.,.,.</li>
            <li>.,.,.,.,.,.,.,.,.,.,.,.,.,.,.,.,.,.,.,.,.,.,.,.,.,.,.,.,.,.,.,.,.,.,.,.,.,.,.,.,.,.,.,.,.,.,.,.,.,.,.,.,.,.,.,.,.,.,.,.,.,.,.,.,.,.,.,.,.,.,.,.,.,.,.,.,.,.</li>
            <li>.,.,.,.,.,.,.,.,.,.,.,.,.,.,.,.,.,.,.,.,.,.,.,.,.,.,.,.,.,.,.,.,.,.,.,.,.,.,.,.,.,.,.,.,.,.,.,.,.,.,.,.,.,.,.,.,.,.,.,.,.,.,.,.,.,.,.,.,.,.,.,.,.,.,.,.,.,.</li>
            <li>.,.,.,.,.,.,.,.,.,.,.,.,.,.,.,.,.,.,.,.,.,.,.,.,.,.,.,.,.,.,.,.,.,.,.,.,.,.,.,.,.,.,.,.,.,.,.,.,.,.,.,.,.,.,.,.,.,.,.,.,.,.,.,.,.,.,.,.,.,.,.,.,.,.,.,.,.,.</li>
            <li>.,.,.,.,.,.,.,.,.,.,.,.,.,.,.,.,.,.,.,.,.,.,.,.,.,.,.,.,.,.,.,.,.,.,.,.,.,.,.,.,.,.,.,.,.,.,.,.,.,.,.,.,.,.,.,.,.,.,.,.,.,.,.,.,.,.,.,.,.,.,.,.,.,.,.,.,.,.</li>
            <li>.,.,.,.,.,.,.,.,.,.,.,.,.,.,.,.,.,.,.,.,.,.,.,.,.,.,.,.,.,.,.,.,.,.,.,.,.,.,.,.,.,.,.,.,.,.,.,.,.,.,.,.,.,.,.,.,.,.,.,.,.,.,.,.,.,.,.,.,.,.,.,.,.,.,.,.,.,.</li>
        </roofGrid>
        <terrainGrid>
            <li>.,.,.,.,.,.,.,.,.,.,.,.,.,.,.,.,.,.,.,.,.,.,.,.,.,.,.,.,.,.,.,.,.,.,.,.,.,.,.,.,.,.,.,.,.,.,.,.,.,.,.,.,.,.,.,.,.,.,.,.,.,.,.,.,.,.,.,.,.,.,.,.,.,.,.,.,.,.</li>
            <li>.,.,.,.,.,.,.,.,.,.,.,.,.,.,.,.,.,.,.,.,.,.,.,.,.,.,.,.,.,.,.,.,.,.,.,.,.,.,.,.,.,.,.,.,.,.,.,.,.,.,.,.,.,.,.,.,.,.,.,.,.,.,.,.,.,.,.,.,.,.,.,.,.,.,.,.,.,.</li>
            <li>.,.,.,.,.,.,.,.,.,.,.,.,.,.,.,.,.,.,.,.,.,.,.,.,.,.,.,.,.,.,.,.,.,.,.,.,.,.,.,.,.,.,.,.,.,.,.,.,.,.,.,.,.,.,.,.,.,.,.,.,.,.,.,.,.,.,.,.,.,.,.,.,.,.,.,.,.,.</li>
            <li>.,.,.,.,.,.,.,.,.,.,.,.,.,.,.,.,.,.,.,.,.,.,.,.,.,.,.,.,.,.,.,.,.,.,.,.,.,.,.,.,.,.,.,.,.,.,.,.,.,.,.,.,.,.,.,.,.,.,.,.,.,.,.,.,.,.,.,.,.,.,.,.,.,.,.,.,.,.</li>
            <li>.,.,.,.,.,.,.,.,.,.,.,.,.,.,.,.,.,.,.,.,.,.,.,.,.,.,.,.,.,.,.,.,.,.,.,.,.,.,.,.,.,.,.,.,.,.,.,.,.,.,.,.,.,.,.,.,.,.,.,.,.,.,.,.,.,.,.,.,.,.,.,.,.,.,.,.,.,.</li>
            <li>.,.,.,.,.,.,WoodPlankFloor,WoodPlankFloor,WoodPlankFloor,WoodPlankFloor,WoodPlankFloor,WoodPlankFloor,WoodPlankFloor,WoodPlankFloor,WoodPlankFloor,WoodPlankFloor,WoodPlankFloor,.,.,.,WoodPlankFloor,WoodPlankFloor,WoodPlankFloor,WoodPlankFloor,WoodPlankFloor,WoodPlankFloor,WoodPlankFloor,WoodPlankFloor,WoodPlankFloor,WoodPlankFloor,WoodPlankFloor,.,.,.,.,.,.,.,.,.,.,.,.,WoodPlankFloor,WoodPlankFloor,WoodPlankFloor,WoodPlankFloor,WoodPlankFloor,WoodPlankFloor,WoodPlankFloor,WoodPlankFloor,WoodPlankFloor,WoodPlankFloor,WoodPlankFloor,.,.,.,.,.,.,.,.,.,.,.,.,.,.,.,.,.,.,.,.,.,.,.,.</li>
            <li>.,.,.,.,.,.,WoodPlankFloor,WoodPlankFloor,WoodPlankFloor,WoodPlankFloor,WoodPlankFloor,WoodPlankFloor,WoodPlankFloor,WoodPlankFloor,WoodPlankFloor,WoodPlankFloor,WoodPlankFloor,.,.,.,WoodPlankFloor,WoodPlankFloor,WoodPlankFloor,WoodPlankFloor,WoodPlankFloor,WoodPlankFloor,WoodPlankFloor,WoodPlankFloor,WoodPlankFloor,WoodPlankFloor,WoodPlankFloor,.,.,.,.,.,.,.,.,.,.,.,.,WoodPlankFloor,WoodPlankFloor,WoodPlankFloor,WoodPlankFloor,WoodPlankFloor,WoodPlankFloor,WoodPlankFloor,WoodPlankFloor,WoodPlankFloor,WoodPlankFloor,WoodPlankFloor,.,.,.,SterileTile,SterileTile,SterileTile,SterileTile,SterileTile,SterileTile,SterileTile,SterileTile,SterileTile,SterileTile,SterileTile,SterileTile,SterileTile,SterileTile,SterileTile,SterileTile,SterileTile,SterileTile,.,.,.</li>
            <li>.,.,.,.,.,.,WoodPlankFloor,WoodPlankFloor,WoodPlankFloor,WoodPlankFloor,WoodPlankFloor,WoodPlankFloor,WoodPlankFloor,WoodPlankFloor,WoodPlankFloor,WoodPlankFloor,WoodPlankFloor,.,.,.,WoodPlankFloor,WoodPlankFloor,WoodPlankFloor,WoodPlankFloor,WoodPlankFloor,WoodPlankFloor,WoodPlankFloor,WoodPlankFloor,WoodPlankFloor,WoodPlankFloor,WoodPlankFloor,.,.,.,.,.,.,.,.,.,.,.,.,WoodPlankFloor,WoodPlankFloor,WoodPlankFloor,WoodPlankFloor,WoodPlankFloor,WoodPlankFloor,WoodPlankFloor,WoodPlankFloor,WoodPlankFloor,WoodPlankFloor,WoodPlankFloor,.,.,.,SterileTile,SterileTile,SterileTile,SterileTile,SterileTile,SterileTile,SterileTile,SterileTile,SterileTile,SterileTile,SterileTile,SterileTile,SterileTile,SterileTile,SterileTile,SterileTile,SterileTile,SterileTile,.,.,.</li>
            <li>.,.,.,.,.,.,WoodPlankFloor,WoodPlankFloor,WoodPlankFloor,WoodPlankFloor,WoodPlankFloor,WoodPlankFloor,WoodPlankFloor,WoodPlankFloor,WoodPlankFloor,WoodPlankFloor,WoodPlankFloor,.,.,.,WoodPlankFloor,WoodPlankFloor,WoodPlankFloor,WoodPlankFloor,WoodPlankFloor,WoodPlankFloor,WoodPlankFloor,WoodPlankFloor,WoodPlankFloor,WoodPlankFloor,WoodPlankFloor,.,.,.,.,.,.,.,.,.,.,.,.,WoodPlankFloor,WoodPlankFloor,WoodPlankFloor,WoodPlankFloor,WoodPlankFloor,WoodPlankFloor,WoodPlankFloor,WoodPlankFloor,WoodPlankFloor,WoodPlankFloor,WoodPlankFloor,.,.,.,SterileTile,SterileTile,SterileTile,SterileTile,SterileTile,SterileTile,SterileTile,SterileTile,SterileTile,SterileTile,SterileTile,SterileTile,SterileTile,SterileTile,SterileTile,SterileTile,SterileTile,SterileTile,.,.,.</li>
            <li>.,.,.,.,.,.,WoodPlankFloor,WoodPlankFloor,WoodPlankFloor,WoodPlankFloor,WoodPlankFloor,WoodPlankFloor,WoodPlankFloor,WoodPlankFloor,WoodPlankFloor,WoodPlankFloor,WoodPlankFloor,.,.,.,WoodPlankFloor,WoodPlankFloor,WoodPlankFloor,WoodPlankFloor,WoodPlankFloor,WoodPlankFloor,WoodPlankFloor,WoodPlankFloor,WoodPlankFloor,WoodPlankFloor,WoodPlankFloor,.,.,.,.,.,.,.,.,.,.,.,.,WoodPlankFloor,WoodPlankFloor,WoodPlankFloor,WoodPlankFloor,WoodPlankFloor,WoodPlankFloor,WoodPlankFloor,WoodPlankFloor,WoodPlankFloor,WoodPlankFloor,WoodPlankFloor,.,.,.,SterileTile,SterileTile,SterileTile,SterileTile,SterileTile,SterileTile,SterileTile,SterileTile,SterileTile,SterileTile,SterileTile,SterileTile,SterileTile,SterileTile,SterileTile,SterileTile,SterileTile,SterileTile,.,.,.</li>
            <li>.,.,.,.,.,.,WoodPlankFloor,WoodPlankFloor,WoodPlankFloor,WoodPlankFloor,WoodPlankFloor,WoodPlankFloor,WoodPlankFloor,WoodPlankFloor,WoodPlankFloor,WoodPlankFloor,WoodPlankFloor,.,.,.,WoodPlankFloor,WoodPlankFloor,WoodPlankFloor,WoodPlankFloor,WoodPlankFloor,WoodPlankFloor,WoodPlankFloor,WoodPlankFloor,WoodPlankFloor,WoodPlankFloor,WoodPlankFloor,.,.,.,.,.,.,.,.,.,.,.,.,WoodPlankFloor,WoodPlankFloor,WoodPlankFloor,WoodPlankFloor,WoodPlankFloor,WoodPlankFloor,WoodPlankFloor,WoodPlankFloor,WoodPlankFloor,WoodPlankFloor,WoodPlankFloor,.,.,.,SterileTile,SterileTile,SterileTile,SterileTile,SterileTile,SterileTile,SterileTile,SterileTile,SterileTile,SterileTile,SterileTile,SterileTile,SterileTile,SterileTile,SterileTile,SterileTile,SterileTile,SterileTile,.,.,.</li>
            <li>.,.,.,.,.,.,WoodPlankFloor,WoodPlankFloor,WoodPlankFloor,WoodPlankFloor,WoodPlankFloor,WoodPlankFloor,WoodPlankFloor,WoodPlankFloor,WoodPlankFloor,WoodPlankFloor,WoodPlankFloor,.,.,.,WoodPlankFloor,WoodPlankFloor,WoodPlankFloor,WoodPlankFloor,WoodPlankFloor,WoodPlankFloor,WoodPlankFloor,WoodPlankFloor,WoodPlankFloor,WoodPlankFloor,WoodPlankFloor,.,.,.,.,.,.,.,.,.,.,.,.,WoodPlankFloor,WoodPlankFloor,WoodPlankFloor,WoodPlankFloor,WoodPlankFloor,WoodPlankFloor,WoodPlankFloor,WoodPlankFloor,WoodPlankFloor,WoodPlankFloor,WoodPlankFloor,.,.,.,SterileTile,SterileTile,SterileTile,SterileTile,SterileTile,SterileTile,SterileTile,SterileTile,SterileTile,SterileTile,SterileTile,SterileTile,SterileTile,SterileTile,SterileTile,SterileTile,SterileTile,SterileTile,.,.,.</li>
            <li>.,.,.,.,.,.,WoodPlankFloor,WoodPlankFloor,WoodPlankFloor,WoodPlankFloor,WoodPlankFloor,WoodPlankFloor,WoodPlankFloor,WoodPlankFloor,WoodPlankFloor,WoodPlankFloor,WoodPlankFloor,.,.,.,WoodPlankFloor,WoodPlankFloor,WoodPlankFloor,WoodPlankFloor,WoodPlankFloor,WoodPlankFloor,WoodPlankFloor,WoodPlankFloor,WoodPlankFloor,WoodPlankFloor,WoodPlankFloor,.,.,.,.,.,.,.,.,.,.,.,.,WoodPlankFloor,WoodPlankFloor,WoodPlankFloor,WoodPlankFloor,WoodPlankFloor,WoodPlankFloor,WoodPlankFloor,WoodPlankFloor,WoodPlankFloor,WoodPlankFloor,WoodPlankFloor,.,.,.,SterileTile,SterileTile,SterileTile,SterileTile,SterileTile,SterileTile,SterileTile,SterileTile,SterileTile,SterileTile,SterileTile,SterileTile,SterileTile,SterileTile,SterileTile,SterileTile,SterileTile,SterileTile,.,.,.</li>
            <li>.,.,.,.,.,.,WoodPlankFloor,WoodPlankFloor,WoodPlankFloor,WoodPlankFloor,WoodPlankFloor,WoodPlankFloor,WoodPlankFloor,WoodPlankFloor,WoodPlankFloor,WoodPlankFloor,WoodPlankFloor,.,.,.,WoodPlankFloor,WoodPlankFloor,WoodPlankFloor,WoodPlankFloor,WoodPlankFloor,WoodPlankFloor,WoodPlankFloor,WoodPlankFloor,WoodPlankFloor,WoodPlankFloor,WoodPlankFloor,.,.,.,.,.,.,.,.,.,.,.,.,WoodPlankFloor,WoodPlankFloor,WoodPlankFloor,WoodPlankFloor,WoodPlankFloor,WoodPlankFloor,WoodPlankFloor,WoodPlankFloor,WoodPlankFloor,WoodPlankFloor,WoodPlankFloor,.,.,.,SterileTile,SterileTile,SterileTile,SterileTile,SterileTile,SterileTile,SterileTile,SterileTile,SterileTile,SterileTile,SterileTile,SterileTile,SterileTile,SterileTile,SterileTile,SterileTile,SterileTile,SterileTile,.,.,.</li>
            <li>.,.,.,.,.,.,WoodPlankFloor,WoodPlankFloor,WoodPlankFloor,WoodPlankFloor,WoodPlankFloor,WoodPlankFloor,WoodPlankFloor,WoodPlankFloor,WoodPlankFloor,WoodPlankFloor,WoodPlankFloor,.,.,.,WoodPlankFloor,WoodPlankFloor,WoodPlankFloor,WoodPlankFloor,WoodPlankFloor,WoodPlankFloor,WoodPlankFloor,WoodPlankFloor,WoodPlankFloor,WoodPlankFloor,WoodPlankFloor,.,.,.,.,.,.,.,.,.,.,.,.,WoodPlankFloor,WoodPlankFloor,WoodPlankFloor,WoodPlankFloor,WoodPlankFloor,WoodPlankFloor,WoodPlankFloor,WoodPlankFloor,WoodPlankFloor,WoodPlankFloor,WoodPlankFloor,.,.,.,SterileTile,SterileTile,SterileTile,SterileTile,SterileTile,SterileTile,SterileTile,SterileTile,SterileTile,SterileTile,SterileTile,SterileTile,SterileTile,SterileTile,SterileTile,SterileTile,SterileTile,SterileTile,.,.,.</li>
            <li>.,.,.,.,.,.,WoodPlankFloor,WoodPlankFloor,WoodPlankFloor,WoodPlankFloor,WoodPlankFloor,WoodPlankFloor,WoodPlankFloor,WoodPlankFloor,WoodPlankFloor,WoodPlankFloor,WoodPlankFloor,.,.,.,WoodPlankFloor,WoodPlankFloor,WoodPlankFloor,WoodPlankFloor,WoodPlankFloor,WoodPlankFloor,WoodPlankFloor,WoodPlankFloor,WoodPlankFloor,WoodPlankFloor,WoodPlankFloor,.,.,.,.,.,.,.,.,.,.,.,.,WoodPlankFloor,WoodPlankFloor,WoodPlankFloor,WoodPlankFloor,WoodPlankFloor,WoodPlankFloor,WoodPlankFloor,WoodPlankFloor,WoodPlankFloor,WoodPlankFloor,WoodPlankFloor,.,.,.,.,.,.,.,.,.,.,.,.,.,.,.,.,.,.,.,.,.,.,.,.</li>
            <li>.,.,.,.,.,.,WoodPlankFloor,WoodPlankFloor,WoodPlankFloor,WoodPlankFloor,WoodPlankFloor,WoodPlankFloor,WoodPlankFloor,WoodPlankFloor,WoodPlankFloor,WoodPlankFloor,WoodPlankFloor,.,.,.,WoodPlankFloor,WoodPlankFloor,WoodPlankFloor,WoodPlankFloor,WoodPlankFloor,WoodPlankFloor,WoodPlankFloor,WoodPlankFloor,WoodPlankFloor,WoodPlankFloor,WoodPlankFloor,.,.,.,.,.,.,.,.,.,.,.,.,WoodPlankFloor,WoodPlankFloor,WoodPlankFloor,WoodPlankFloor,WoodPlankFloor,WoodPlankFloor,WoodPlankFloor,WoodPlankFloor,WoodPlankFloor,WoodPlankFloor,WoodPlankFloor,.,.,.,.,.,.,.,.,.,.,.,.,.,.,.,.,.,.,.,.,.,.,.,.</li>
            <li>.,.,.,.,.,.,WoodPlankFloor,WoodPlankFloor,WoodPlankFloor,WoodPlankFloor,WoodPlankFloor,WoodPlankFloor,WoodPlankFloor,WoodPlankFloor,WoodPlankFloor,WoodPlankFloor,WoodPlankFloor,.,.,.,WoodPlankFloor,WoodPlankFloor,WoodPlankFloor,WoodPlankFloor,WoodPlankFloor,WoodPlankFloor,WoodPlankFloor,WoodPlankFloor,WoodPlankFloor,WoodPlankFloor,WoodPlankFloor,.,.,.,.,.,.,.,.,.,.,.,.,WoodPlankFloor,WoodPlankFloor,WoodPlankFloor,WoodPlankFloor,WoodPlankFloor,WoodPlankFloor,WoodPlankFloor,WoodPlankFloor,WoodPlankFloor,WoodPlankFloor,WoodPlankFloor,.,.,.,.,.,.,.,.,.,.,.,.,.,.,.,.,.,.,.,.,.,.,.,.</li>
            <li>.,.,.,.,.,.,WoodPlankFloor,WoodPlankFloor,WoodPlankFloor,WoodPlankFloor,WoodPlankFloor,WoodPlankFloor,WoodPlankFloor,WoodPlankFloor,WoodPlankFloor,WoodPlankFloor,WoodPlankFloor,.,.,.,WoodPlankFloor,WoodPlankFloor,WoodPlankFloor,WoodPlankFloor,WoodPlankFloor,WoodPlankFloor,WoodPlankFloor,WoodPlankFloor,WoodPlankFloor,WoodPlankFloor,WoodPlankFloor,.,.,.,.,.,.,.,.,.,.,.,.,WoodPlankFloor,WoodPlankFloor,WoodPlankFloor,WoodPlankFloor,WoodPlankFloor,WoodPlankFloor,WoodPlankFloor,WoodPlankFloor,WoodPlankFloor,WoodPlankFloor,WoodPlankFloor,.,.,.,.,.,.,.,.,.,.,.,.,.,.,.,.,.,.,.,.,.,.,.,.</li>
            <li>.,.,.,.,.,.,WoodPlankFloor,WoodPlankFloor,WoodPlankFloor,WoodPlankFloor,WoodPlankFloor,WoodPlankFloor,WoodPlankFloor,WoodPlankFloor,WoodPlankFloor,WoodPlankFloor,WoodPlankFloor,.,.,.,WoodPlankFloor,WoodPlankFloor,WoodPlankFloor,WoodPlankFloor,WoodPlankFloor,WoodPlankFloor,WoodPlankFloor,WoodPlankFloor,WoodPlankFloor,WoodPlankFloor,WoodPlankFloor,.,.,.,.,.,.,.,.,.,.,.,.,WoodPlankFloor,WoodPlankFloor,WoodPlankFloor,WoodPlankFloor,WoodPlankFloor,WoodPlankFloor,WoodPlankFloor,WoodPlankFloor,WoodPlankFloor,WoodPlankFloor,WoodPlankFloor,.,.,.,.,.,.,.,.,.,.,.,.,.,.,.,.,.,.,.,.,.,.,.,.</li>
            <li>.,.,.,.,.,.,WoodPlankFloor,WoodPlankFloor,WoodPlankFloor,WoodPlankFloor,WoodPlankFloor,WoodPlankFloor,WoodPlankFloor,WoodPlankFloor,WoodPlankFloor,WoodPlankFloor,WoodPlankFloor,.,.,.,WoodPlankFloor,WoodPlankFloor,WoodPlankFloor,WoodPlankFloor,WoodPlankFloor,WoodPlankFloor,WoodPlankFloor,WoodPlankFloor,WoodPlankFloor,WoodPlankFloor,WoodPlankFloor,.,.,.,.,.,.,.,.,.,.,.,.,WoodPlankFloor,WoodPlankFloor,WoodPlankFloor,WoodPlankFloor,WoodPlankFloor,WoodPlankFloor,WoodPlankFloor,WoodPlankFloor,WoodPlankFloor,WoodPlankFloor,WoodPlankFloor,.,.,.,.,.,.,.,.,.,.,.,.,.,.,.,.,.,.,.,.,.,.,.,.</li>
            <li>.,.,.,.,.,.,WoodPlankFloor,WoodPlankFloor,WoodPlankFloor,WoodPlankFloor,WoodPlankFloor,WoodPlankFloor,WoodPlankFloor,WoodPlankFloor,WoodPlankFloor,WoodPlankFloor,WoodPlankFloor,.,.,.,WoodPlankFloor,WoodPlankFloor,WoodPlankFloor,WoodPlankFloor,WoodPlankFloor,WoodPlankFloor,WoodPlankFloor,WoodPlankFloor,WoodPlankFloor,WoodPlankFloor,WoodPlankFloor,.,.,.,.,.,.,.,.,.,.,.,.,WoodPlankFloor,WoodPlankFloor,WoodPlankFloor,WoodPlankFloor,WoodPlankFloor,WoodPlankFloor,WoodPlankFloor,WoodPlankFloor,WoodPlankFloor,WoodPlankFloor,WoodPlankFloor,.,.,.,.,.,.,.,.,.,.,.,.,.,.,.,.,.,.,.,.,.,.,.,.</li>
            <li>.,.,.,.,.,.,WoodPlankFloor,WoodPlankFloor,WoodPlankFloor,WoodPlankFloor,WoodPlankFloor,WoodPlankFloor,WoodPlankFloor,WoodPlankFloor,WoodPlankFloor,WoodPlankFloor,WoodPlankFloor,.,.,.,WoodPlankFloor,WoodPlankFloor,WoodPlankFloor,WoodPlankFloor,WoodPlankFloor,WoodPlankFloor,WoodPlankFloor,WoodPlankFloor,WoodPlankFloor,WoodPlankFloor,WoodPlankFloor,.,.,.,.,.,.,.,.,.,.,.,.,WoodPlankFloor,WoodPlankFloor,WoodPlankFloor,WoodPlankFloor,WoodPlankFloor,WoodPlankFloor,WoodPlankFloor,WoodPlankFloor,WoodPlankFloor,WoodPlankFloor,WoodPlankFloor,.,.,.,.,.,.,.,.,.,.,.,.,.,.,.,.,.,.,.,.,.,.,.,.</li>
            <li>.,.,.,.,.,.,WoodPlankFloor,WoodPlankFloor,WoodPlankFloor,WoodPlankFloor,WoodPlankFloor,WoodPlankFloor,WoodPlankFloor,WoodPlankFloor,WoodPlankFloor,WoodPlankFloor,WoodPlankFloor,.,.,.,WoodPlankFloor,WoodPlankFloor,WoodPlankFloor,WoodPlankFloor,WoodPlankFloor,WoodPlankFloor,WoodPlankFloor,WoodPlankFloor,WoodPlankFloor,WoodPlankFloor,WoodPlankFloor,.,.,.,.,.,.,.,.,.,.,.,.,WoodPlankFloor,WoodPlankFloor,WoodPlankFloor,WoodPlankFloor,WoodPlankFloor,WoodPlankFloor,WoodPlankFloor,WoodPlankFloor,WoodPlankFloor,WoodPlankFloor,WoodPlankFloor,.,.,.,.,.,.,.,.,.,.,.,.,.,.,.,.,.,.,.,.,.,.,.,.</li>
            <li>.,.,.,.,.,.,.,.,.,.,.,.,.,.,.,.,.,.,.,.,.,.,.,.,.,.,.,.,.,.,.,.,.,.,.,.,.,.,.,.,.,.,.,.,.,.,.,.,.,.,.,.,.,.,.,.,.,.,.,.,.,.,.,.,.,.,.,.,.,.,.,.,.,.,.,.,.,.</li>
            <li>.,.,.,.,.,.,.,.,.,.,.,.,.,.,.,.,.,.,.,.,.,.,.,.,.,.,.,.,.,.,.,.,.,.,.,.,.,.,.,.,.,.,.,.,.,.,.,.,.,.,.,.,.,.,.,.,.,.,.,.,.,.,.,.,.,.,.,.,.,.,.,.,.,.,.,.,.,.</li>
            <li>.,.,.,.,.,.,.,.,.,.,.,.,.,.,.,.,.,.,.,.,.,.,.,.,.,.,.,.,.,.,.,.,.,.,.,.,.,.,.,.,.,.,.,.,.,.,.,.,.,.,.,.,.,.,.,.,.,.,.,.,.,.,.,.,.,.,.,.,.,.,.,.,.,.,.,.,.,.</li>
            <li>.,.,.,.,.,.,.,.,.,.,.,.,.,.,.,.,.,.,.,.,.,.,.,.,.,.,.,.,.,.,.,.,.,.,.,.,.,.,.,.,.,.,.,.,.,.,.,.,.,.,.,.,.,.,.,.,.,.,.,.,.,.,.,.,.,.,.,.,.,.,.,.,.,.,.,.,.,.</li>
            <li>.,.,.,.,.,.,.,.,.,.,.,.,.,.,.,.,.,.,.,.,.,.,.,.,.,.,.,.,.,.,.,.,.,.,.,.,.,.,.,.,.,.,.,.,.,.,.,.,.,.,.,.,.,.,.,.,.,.,.,.,.,.,.,.,.,.,.,.,.,.,.,.,.,.,.,.,.,.</li>
            <li>.,.,.,.,.,.,.,.,.,.,.,.,.,.,.,.,.,.,.,.,.,.,.,.,.,.,.,.,.,.,.,.,.,.,.,.,.,.,.,.,.,.,.,.,.,.,.,.,.,.,.,.,.,.,.,.,.,.,.,.,.,.,.,.,.,.,.,.,.,.,.,.,.,.,.,.,.,.</li>
            <li>.,.,.,.,.,.,.,.,.,.,.,.,.,.,.,.,.,.,.,.,.,.,.,.,.,.,.,.,.,.,.,.,.,.,.,.,.,.,.,.,.,.,.,.,.,.,.,.,.,.,.,.,.,.,.,.,.,.,.,.,.,.,.,.,.,.,.,.,.,.,.,.,.,.,.,.,.,.</li>
            <li>.,.,.,.,.,.,.,.,.,.,.,.,.,.,.,.,.,.,.,.,.,.,.,.,.,.,.,.,.,.,.,.,.,.,.,.,.,.,.,.,.,.,.,.,FineTileMarble,FineTileMarble,FineTileMarble,FineTileMarble,FineTileMarble,FineTileMarble,FineTileMarble,FineTileMarble,FineTileMarble,.,.,.,.,.,SterileTile,SterileTile,SterileTile,SterileTile,SterileTile,SterileTile,SterileTile,SterileTile,SterileTile,.,.,.,.,.,.,.,.,.,.,.</li>
            <li>.,.,.,.,.,.,.,.,.,.,.,.,.,.,.,.,.,.,.,.,.,.,.,.,.,.,.,.,.,.,.,.,.,.,.,.,.,.,.,.,.,.,.,.,FineTileMarble,FineTileMarble,FineTileMarble,FineTileMarble,FineTileMarble,FineTileMarble,FineTileMarble,FineTileMarble,FineTileMarble,.,.,.,.,.,SterileTile,SterileTile,SterileTile,SterileTile,SterileTile,SterileTile,SterileTile,SterileTile,SterileTile,.,.,.,.,.,.,.,.,.,.,.</li>
            <li>.,.,.,.,.,.,.,.,.,.,.,.,.,.,.,.,.,.,.,.,.,.,.,.,.,.,.,.,.,.,.,.,.,.,.,.,.,.,.,.,.,.,.,.,FineTileMarble,FineTileMarble,FineTileMarble,FineTileMarble,FineTileMarble,FineTileMarble,FineTileMarble,FineTileMarble,FineTileMarble,.,.,.,.,.,SterileTile,SterileTile,SterileTile,SterileTile,SterileTile,SterileTile,SterileTile,SterileTile,SterileTile,.,.,.,.,.,.,.,.,.,.,.</li>
            <li>.,.,.,.,.,.,.,.,.,.,.,.,.,.,.,.,.,.,.,.,.,.,.,.,.,.,.,.,.,.,.,.,.,.,.,.,.,.,.,.,.,.,.,.,FineTileMarble,FineTileMarble,FineTileMarble,FineTileMarble,FineTileMarble,FineTileMarble,FineTileMarble,FineTileMarble,FineTileMarble,.,.,.,.,.,SterileTile,SterileTile,SterileTile,SterileTile,SterileTile,SterileTile,SterileTile,SterileTile,SterileTile,.,.,.,.,.,.,.,.,.,.,.</li>
            <li>.,.,.,.,.,.,.,.,.,.,.,.,.,.,.,.,.,.,.,.,.,.,.,.,.,.,.,.,.,.,.,.,.,.,.,.,.,.,.,.,.,.,.,.,FineTileMarble,FineTileMarble,FineTileMarble,FineTileMarble,FineTileMarble,FineTileMarble,FineTileMarble,FineTileMarble,FineTileMarble,.,.,.,.,.,SterileTile,SterileTile,SterileTile,SterileTile,SterileTile,SterileTile,SterileTile,SterileTile,SterileTile,.,.,.,.,.,.,.,.,.,.,.</li>
            <li>.,.,.,.,.,.,.,.,.,.,.,.,.,.,.,.,.,.,.,.,.,.,.,.,.,.,.,.,.,.,.,.,.,.,.,.,.,.,.,.,.,.,.,.,FineTileMarble,FineTileMarble,FineTileMarble,FineTileMarble,FineTileMarble,FineTileMarble,FineTileMarble,FineTileMarble,FineTileMarble,.,.,.,.,.,SterileTile,SterileTile,SterileTile,SterileTile,SterileTile,SterileTile,SterileTile,SterileTile,SterileTile,.,.,.,.,.,.,.,.,.,.,.</li>
            <li>.,.,.,.,.,.,.,.,.,.,.,.,.,.,.,.,.,.,.,.,.,.,.,.,.,.,.,.,.,.,.,.,.,.,.,.,.,.,.,.,.,.,.,.,FineTileMarble,FineTileMarble,FineTileMarble,FineTileMarble,FineTileMarble,FineTileMarble,FineTileMarble,FineTileMarble,FineTileMarble,.,.,.,.,.,SterileTile,SterileTile,SterileTile,SterileTile,SterileTile,SterileTile,SterileTile,SterileTile,SterileTile,.,.,.,.,.,.,.,.,.,.,.</li>
            <li>.,.,.,.,.,.,.,.,.,.,.,.,.,.,.,.,.,.,.,.,.,.,.,.,.,.,.,.,.,.,.,.,.,.,.,.,.,.,.,.,.,.,.,.,FineTileMarble,FineTileMarble,FineTileMarble,FineTileMarble,FineTileMarble,FineTileMarble,FineTileMarble,FineTileMarble,FineTileMarble,.,.,.,.,.,SterileTile,SterileTile,SterileTile,SterileTile,SterileTile,SterileTile,SterileTile,SterileTile,SterileTile,.,.,.,.,.,.,.,.,.,.,.</li>
            <li>.,.,.,.,.,.,.,.,.,.,.,.,.,.,.,.,.,.,.,.,.,.,.,.,.,.,.,.,.,.,.,.,.,.,.,.,.,.,.,.,.,.,.,.,FineTileMarble,FineTileMarble,FineTileMarble,FineTileMarble,FineTileMarble,FineTileMarble,FineTileMarble,FineTileMarble,FineTileMarble,.,.,.,.,.,.,.,.,.,.,.,.,.,.,.,.,.,.,.,.,.,.,.,.,.</li>
            <li>.,.,.,.,.,.,.,.,.,.,.,.,.,.,.,.,.,.,.,.,.,.,.,.,.,.,.,.,.,.,.,.,.,.,.,.,.,.,.,.,.,.,.,.,FineTileMarble,FineTileMarble,FineTileMarble,FineTileMarble,FineTileMarble,FineTileMarble,FineTileMarble,FineTileMarble,FineTileMarble,.,.,.,.,.,.,.,.,.,.,.,.,.,.,.,.,.,.,.,.,.,.,.,.,.</li>
            <li>.,.,.,.,.,.,.,.,.,.,.,.,.,.,.,.,.,.,.,.,.,.,.,.,.,.,.,.,.,.,.,.,.,.,.,.,.,.,.,.,.,.,.,.,FineTileMarble,FineTileMarble,FineTileMarble,FineTileMarble,FineTileMarble,FineTileMarble,FineTileMarble,FineTileMarble,FineTileMarble,.,.,.,.,.,.,.,.,.,.,.,.,.,.,.,.,.,.,.,.,.,.,.,.,.</li>
            <li>.,.,.,.,.,.,.,.,.,.,.,.,.,.,.,.,.,.,.,.,.,.,.,.,.,.,.,.,.,.,.,.,.,.,.,.,.,.,.,.,.,.,.,.,FineTileMarble,FineTileMarble,FineTileMarble,FineTileMarble,FineTileMarble,FineTileMarble,FineTileMarble,FineTileMarble,FineTileMarble,.,.,.,.,.,.,.,.,.,.,.,.,.,.,.,.,.,.,.,.,.,.,.,.,.</li>
            <li>.,.,.,.,.,.,.,.,.,.,.,.,.,.,.,.,.,.,.,.,.,.,.,.,.,.,.,.,.,.,.,.,.,.,.,.,.,.,.,.,.,.,.,.,FineTileMarble,FineTileMarble,FineTileMarble,FineTileMarble,FineTileMarble,FineTileMarble,FineTileMarble,FineTileMarble,FineTileMarble,.,.,.,.,.,.,.,.,.,.,.,.,.,.,.,.,.,.,.,.,.,.,.,.,.</li>
            <li>.,.,.,.,.,.,.,.,.,.,.,.,.,.,.,.,.,.,.,.,.,.,.,.,.,.,.,.,.,.,.,.,.,.,.,.,.,.,.,.,.,.,.,.,FineTileMarble,FineTileMarble,FineTileMarble,FineTileMarble,FineTileMarble,FineTileMarble,FineTileMarble,FineTileMarble,FineTileMarble,.,.,.,.,.,.,.,.,.,.,.,.,.,.,.,.,.,.,.,.,.,.,.,.,.</li>
            <li>.,.,.,.,.,.,.,.,.,.,.,.,.,.,.,.,.,.,.,.,.,.,.,.,.,.,.,.,.,.,.,.,.,.,.,.,.,.,.,.,.,.,.,.,FineTileMarble,FineTileMarble,FineTileMarble,FineTileMarble,FineTileMarble,FineTileMarble,FineTileMarble,FineTileMarble,FineTileMarble,.,.,.,.,.,.,.,.,.,.,.,.,.,.,.,.,.,.,.,.,.,.,.,.,.</li>
            <li>.,.,.,.,.,.,.,.,.,.,.,.,.,.,.,.,.,.,.,.,.,.,.,.,.,.,.,.,.,.,.,.,.,.,.,.,.,.,.,.,.,.,.,.,FineTileMarble,FineTileMarble,FineTileMarble,FineTileMarble,FineTileMarble,FineTileMarble,FineTileMarble,FineTileMarble,FineTileMarble,.,.,.,.,.,.,.,.,.,.,.,.,.,.,.,.,.,.,.,.,.,.,.,.,.</li>
            <li>.,.,.,.,.,.,.,.,.,.,.,.,.,.,.,.,.,.,.,.,.,.,.,.,.,.,.,.,.,.,.,.,.,.,.,.,.,.,.,.,.,.,.,.,FineTileMarble,FineTileMarble,FineTileMarble,FineTileMarble,FineTileMarble,FineTileMarble,FineTileMarble,FineTileMarble,FineTileMarble,.,.,.,.,.,.,.,.,.,.,.,.,.,.,.,.,.,.,.,.,.,.,.,.,.</li>
            <li>.,.,.,.,.,.,.,.,.,.,.,.,.,.,.,.,.,.,.,.,.,.,.,.,.,.,.,.,.,.,.,.,.,.,.,.,.,.,.,.,.,.,.,.,FineTileMarble,FineTileMarble,FineTileMarble,FineTileMarble,FineTileMarble,FineTileMarble,FineTileMarble,FineTileMarble,FineTileMarble,.,.,.,.,.,.,.,.,.,.,.,.,.,.,.,.,.,.,.,.,.,.,.,.,.</li>
            <li>.,.,.,.,.,.,.,.,.,.,.,.,.,.,.,.,.,.,.,.,.,.,.,.,.,.,.,.,.,.,.,.,.,.,.,.,.,.,.,.,.,.,.,.,.,.,.,.,.,.,.,.,.,.,.,.,.,.,.,.,.,.,.,.,.,.,.,.,.,.,.,.,.,.,.,.,.,.</li>
            <li>.,.,.,.,.,.,.,.,.,.,.,.,.,.,.,.,.,.,.,.,.,.,.,.,.,.,.,.,.,.,.,.,.,.,.,.,.,.,.,.,.,.,.,.,.,.,.,.,.,.,.,.,.,.,.,.,.,.,.,.,.,.,.,.,.,.,.,.,.,.,.,.,.,.,.,.,.,.</li>
            <li>.,.,.,.,.,.,.,.,.,.,.,.,.,.,.,.,.,.,.,.,.,.,.,.,.,.,.,.,.,.,.,.,.,.,.,.,.,.,.,.,.,.,.,.,.,.,.,.,.,.,.,.,.,.,.,.,.,.,.,.,.,.,.,.,.,.,.,.,.,.,.,.,.,.,.,.,.,.</li>
            <li>.,.,.,.,.,.,.,.,.,.,.,.,.,.,.,.,.,.,.,.,.,.,.,.,.,.,.,.,.,.,.,.,.,.,.,.,.,.,.,.,.,.,.,.,.,.,.,.,.,.,.,.,.,.,.,.,.,.,.,.,.,.,.,.,.,.,.,.,.,.,.,.,.,.,.,.,.,.</li>
            <li>.,.,.,.,.,.,.,.,.,.,.,.,.,.,.,.,.,.,.,.,.,.,.,.,.,.,.,.,.,.,.,.,.,.,.,.,.,.,.,.,.,.,.,.,.,.,.,.,.,.,.,.,.,.,.,.,.,.,.,.,.,.,.,.,.,.,.,.,.,.,.,.,.,.,.,.,.,.</li>
            <li>.,.,.,.,.,.,.,.,.,.,.,.,.,.,.,.,.,.,.,.,.,.,.,.,.,.,.,.,.,.,.,.,.,.,.,.,.,.,.,.,.,.,.,.,.,.,.,.,.,.,.,.,.,.,.,.,.,.,.,.,.,.,.,.,.,.,.,.,.,.,.,.,.,.,.,.,.,.</li>
            <li>.,.,.,.,.,.,.,.,.,.,.,.,.,.,.,.,.,.,.,.,.,.,.,.,.,.,.,.,.,.,.,.,.,.,.,.,.,.,.,.,.,.,.,.,.,.,.,.,.,.,.,.,.,.,.,.,.,.,.,.,.,.,.,.,.,.,.,.,.,.,.,.,.,.,.,.,.,.</li>
            <li>.,.,.,.,.,.,.,.,.,.,.,.,.,.,.,.,.,.,.,.,.,.,.,.,.,.,.,.,.,.,.,.,.,.,.,.,.,.,.,.,.,.,.,.,.,.,.,.,.,.,.,.,.,.,.,.,.,.,.,.,.,.,.,.,.,.,.,.,.,.,.,.,.,.,.,.,.,.</li>
            <li>.,.,.,.,.,.,.,.,.,.,.,.,.,.,.,.,.,.,.,.,.,.,.,.,.,.,.,.,.,.,.,.,.,.,.,.,.,.,.,.,.,.,.,.,.,.,.,.,.,.,.,.,.,.,.,.,.,.,.,.,.,.,.,.,.,.,.,.,.,.,.,.,.,.,.,.,.,.</li>
            <li>.,.,.,.,.,.,.,.,.,.,.,.,.,.,.,.,.,.,.,.,.,.,.,.,.,.,.,.,.,.,.,.,.,.,.,.,.,.,.,.,.,.,.,.,.,.,.,.,.,.,.,.,.,.,.,.,.,.,.,.,.,.,.,.,.,.,.,.,.,.,.,.,.,.,.,.,.,.</li>
            <li>.,.,.,.,.,.,.,.,.,.,.,.,.,.,.,.,.,.,.,.,.,.,.,.,.,.,.,.,.,.,.,.,.,.,.,.,.,.,.,.,.,.,.,.,.,.,.,.,.,.,.,.,.,.,.,.,.,.,.,.,.,.,.,.,.,.,.,.,.,.,.,.,.,.,.,.,.,.</li>
        </terrainGrid>
        <forceGenerateRoof>true</forceGenerateRoof>
        <needRoofClearance>true</needRoofClearance>
        <tags>
            <li>settlement</li>
            <li>seanbaeg</li>
        </tags>
        <modRequirements>
            <li>ludeon.rimworld.biotech</li>
        </modRequirements>
    </KCSG.StructureLayoutDef>
</Defs>
